Workbook

Sheet RESUMO
B2: DETALHAMENTO DO FATURAMENTO
B4: DISPONÍVEL PARA FATURAR | D4: FATURADO | E4: % DO FATURADO
B5: TOTAL GERAL | C5: =C7+C8+C9 -> 20 | D5: =SUMIF(SiteVisitP1[Data],">0",SiteVisitP1[Valor da Parcela])+SUMIF(Parcela1[Data],">0",Parcela1[Coluna1])+SUMIF(SiteVisitP110[NF],">0",SiteVisitP110[Valor da Parcela]) -> 0 | E5: =IF(D5=0,0,D5/C5) -> 0
B7: TOTAL - 7.02 | C7: =SUM(Parcela1[Coluna1]) -> 10 | D7: =SUM(SUMIF(Parcela1[NF],"<>"&"",Parcela1[Coluna1])) -> 0 | E7: =IF(D7=0,0,D7/C7) -> 0 | G7: =C7-D7 -> 10
B8: TOTAL - 7.03 | C8: =SUM(SiteVisitP1[Valor da Parcela]) -> 10 | D8: =SUMIF(SiteVisitP1[NF],">0",SiteVisitP1[Valor da Parcela]) -> 0 | E8: =IF(D8=0,0,D8/C8) -> 0
B9: TOTAL - 31.01 | C9: =SUM(SiteVisitP110[Valor da Parcela]) -> 0 | D9: =SUMIF(SiteVisitP110[NF],">0",SiteVisitP110[Valor da Parcela]) -> 0 | E9: =IF(D9=0,0,D9/C9) -> 0

Sheet PRIORIDADES
A3: Rótulos de Linha | B3: Soma de Total | C3: Contagem de UF
A4: BR_CE_FORTALEZA_Tax | B4: 4756.272 | C4: 12
A5: BR_PB_BOA VENTURA_Tax | B5: 4753.298 | C5: 9
A6: BR_CE_BREJO SANTO_Tax | B6: 4753.298 | C6: 9
A7: BR_SP_RIO DAS PEDRAS_Tax | B7: 4368.513 | C7: 6
A8: BR_RN_SANTA CRUZ_Tax | B8: 4062.816 | C8: 6
A9: BR_PE_RECIFE_Tax | B9: 3077.523 | C9: 5
A10: BR_SP_MAUA_Tax | B10: 3000 | C10: 1
A11: BR_CE_JUAZEIRO DO NORTE_Tax | B11: 2997.96 | C11: 8
A12: BR_SP_SANTA BARBARA D'OESTE_Tax | B12: 2846.178 | C12: 1
A13: BR_GO_ALTO PARAISO DE GOIAS_Tax | B13: 2815.344 | C13: 1
A14: BR_BA_VALENCA_Tax | B14: 2649.429 | C14: 1
A15: BR_BA_PIRAI DO NORTE_Tax | B15: 2649.429 | C15: 1
... A74: BR_GO_ORIZONA_Tax | B74: 39.022 | C74: 1
A75: (vazio)
A76: Total Geral | B76: 87951.994 | C76: 234

Sheet 7.03
C1: FATURAR POR PO | N1: =SUBTOTAL(9,SiteVisitP1[Valor da Parcela]) -> 10
A2: CC | B2: CÓDIGO FAT | C2: MUNICÍPIO | D2: UF | E2: SITE NAME | F2: OPERADORA | G2: PO | H2: LINE | I2: DU | J2: ItemCode | K2: Preço | L2: Qty | M2: Total | N2: Proporção | O2: Valor da Parcela | P2: NF | Q2: Data | U2: UF | V2: CC
A3: NE2 | B3: 7.03 | C3: BR_CE_AQUIRAZ_Tax | D3: CE | E3: CEAQU07 | F3: CLARO | G3: 6211HG3360340-1482 | H3: 1 | I3: 20250326476411 | J3: 8812441617 | K3: 10 | L3: 1,0000000000 | M3: 10 | N3: 1 | O3: 10
U135: MS | V135: CO
U136: TO | V136: CO
U137: RO | V137: CO
B251: MÁXIMO DE 25 LINHAS | I251: TOTAL DA NF | K251: =SUBTOTAL(9,M3:M249) -> 10
B253: PO | C253: LINE | D253: ="PO "&B253&" LINE "&C253&" " -> PO PO LINE LINE | I253: PIS 0,65% | J253: 0.0065 | K253: =ROUND(J253*K251,2) -> 0.07 | M253: IRRF 1,5% | N253: 0.015 | O253: =ROUND(N253*K251,2) -> 0.15
I254: COFINS 3% | J254: 0.03 | K254: =ROUND(J254*K251,2) -> 0.3 | M254: CSLL 1% | N254: 0.01 | O254: =ROUND(N254*K251,2) -> 0.1
B256: 6211HG3360338-553 | C256: 2 | D256: ="PO "&B256&" LINE "&C256&" " -> PO 6211HG3360338-553 LINE 2 | I256: LÍQUIDO NF | K256: =K251-K253-K254-O253-O254 -> 9.38
B257: 6211HG3360338-418 | C257: 2 | D257: ="PO "&B257&" LINE "&C257&" " -> PO 6211HG3360338-418 LINE 2
B258: 6211HG3360338-435 | C258: 1 | D258: ="PO "&B258&" LINE "&C258&" " -> PO 6211HG3360338-435 LINE 1 | I258: Elaboração de projetos de obras de construção civil e elétrica, referente a adequação de infraestrutura, instalação e montagem de equipamentos de rede de telefonia celular, conforme pedidos de compra abaixo:
I259: =CONCATENATE("PO: ",D256,"/",E256,", ",D257,"/",E257,", ",D258,"/",E258,", ",D259,"/",E259,", ",D260,"/",E260,", ",D261,"/",E261,", ",D262,"/",E262,", ",D263,"/",E263,", ",D264,"/",E264,", ",D265,"/",E265,", ",D266,"/",E266,", ",D267,"/",E267,", ",D268,"/",E268,", ",D269,"/",E269,", ",D270,"/",E270,", ",D271,"/",E271,", ",D272,"/",E272,", ",D273,"/",E273,", ",D274,"/",E274,", ",D275,"/",E275,", ",D276,"/",E276,", ",D277,"/",E277,", ",D278,"/",E278,", ",D279,"/",E279,", ",D280,"/",E280,", ",D281,"/",E281,", ",D282,"/",E282,", ",D283,"/",E283,", ",D284,"/",E284,", ",D285,"/",E285,", ",D286,"/",E286,", ",D287,"/",E287,", ",D288,"/",E288,", ",D289,"/",E289,", ",D290,"/",E290,", ",D291,"/",E291,", ",D292,"/",E292,", ",D293,"/",E293,", ",D294,"/",E294,", ",D295,"/",E295,", ",D296,"/",E296,", ",D297,"/",E297,", ",D298,"/",E298,", ",D299,"/",E299,", ",D300,"/",E300,", ",D301,"/",E301,", ",D302,"/",E302,", ",D303,"/",E303,", ",D304,"/",E304,", ",D305,"/",E305,", ",D306,"/",E306,", ",D307,"/",E307,", ",D308,"/",E308,", ",D309,"/",E309,", ",D310,"/",E310,", ",D311,"/",E311,", ",D312,"/",E312,", ",D313,"/",E313,", ",D314,"/",E314,", ",D315,"/",E315) -> PO: PO 6211HG3360338-553 LINE 2 /, PO 6211HG3360338-418 LINE 2 /, PO 6211HG3360338-435 LINE 1 /, /, /, /, /, /, /, /, /, /, /, /, /, /, /, /, /, /, /, /, /, /, /, /, /, /, /, /, /, /, /, /, /, /, /, /, /, /, /, /, /, /, /, /, /, /, /, /, /, /, /, /, /, /, /, /, /, /
I261: =CONCATENATE("Retenções: ",I253," ","R$ ",K253," ",I254," ","R$ ",K254," ",M253," ","R$ ",O253," ",M254," ","R$ ",O254) -> Retenções: PIS 0,65% R$ 0,07 COFINS 3% R$ 0,3 IRRF 1,5% R$ 0,15 CSLL 1% R$ 0,1
G263: 10.519.123/0001-97

Sheet 31.01
C1: FATURAR POR PO | N1: =SUBTOTAL(9,SiteVisitP110[Valor da Parcela]) -> 0
A2: CC | B2: CÓDIGO FAT | C2: MUNICÍPIO | D2: UF | E2: SITE NAME | F2: OPERADORA | G2: PO | H2: LINE | I2: DU | J2: ItemCode | K2: Preço | L2: Qty | M2: Total | N2: Proporção | O2: Valor da Parcela | P2: NF | Q2: Data | U2: UF | V2: CC
U18: MS | V18: CO
U19: TO | V19: CO
U20: RO | V20: CO
B138: MÁXIMO DE 25 LINHAS | I138: TOTAL DA NF | K138: =SUBTOTAL(9,M3:M136) -> 0
B140: PO | C140: LINE | D140: ="PO "&B140&" LINE "&C140&" " -> PO PO LINE LINE | I140: PIS 0,65% | J140: 0.0065 | K140: =ROUND(J140*K138,2) -> 0 | M140: IRRF 1,5% | N140: 0.015 | O140: =ROUND(N140*K138,2) -> 0
I141: COFINS 3% | J141: 0.03 | K141: =ROUND(J141*K138,2) -> 0 | M141: CSLL 1% | N141: 0.01 | O141: =ROUND(N141*K138,2) -> 0
B143: 6211HG3453276-56 | C143: 1 | D143: ="PO "&B143&" LINE "&C143&" " -> PO 6211HG3453276-56 LINE 1 | I143: LÍQUIDO NF | K143: =K138-K140-K141-O140-O141 -> 0
I145: Serviço técnicos em telecomunicações, conforme pedidos de compra abaixo:
I146: =CONCATENATE("PO: ",D143,"/",E143,", ",D144,"/",E144,", ",D145,"/",E145,", ",D146,"/",E146,", ",D147,"/",E147,", ",D148,"/",E148,", ",D149,"/",E149,", ",D150,"/",E150,", ",D151,"/",E151,", ",D152,"/",E152,", ",D153,"/",E153,", ",D154,"/",E154,", ",D155,"/",E155,", ",D156,"/",E156,", ",D157,"/",E157,", ",D158,"/",E158,", ",D159,"/",E159,", ",D160,"/",E160,", ",D161,"/",E161,", ",D162,"/",E162,", ",D163,"/",E163,", ",D164,"/",E164,", ",D165,"/",E165,", ",D166,"/",E166,", ",D167,"/",E167,", ",D168,"/",E168,", ",D169,"/",E169,", ",D170,"/",E170,", ",D171,"/",E171,", ",D172,"/",E172,", ",D173,"/",E173,", ",D174,"/",E174,", ",D175,"/",E175,", ",D176,"/",E176,", ",D177,"/",E177,", ",D178,"/",E178,", ",D179,"/",E179,", ",D180,"/",E180,", ",D181,"/",E181,", ",D182,"/",E182,", ",D183,"/",E183,", ",D184,"/",E184,", ",D185,"/",E185,", ",D186,"/",E186,", ",D187,"/",E187,", ",D188,"/",E188,", ",D189,"/",E189,", ",D190,"/",E190,", ",D191,"/",E191,", ",D192,"/",E192,", ",D193,"/",E193,", ",D194,"/",E194,", ",D195,"/",E195,", ",D196,"/",E196,", ",D197,"/",E197,", ",D198,"/",E198,", ",D199,"/",E199,", ",D200,"/",E200,", ",D201,"/",E201,", ",D202,"/",E202) -> PO: PO 6211HG3453276-56 LINE 1 /, /, /, /, /, /, /, /, /, /, /, /, /, /, /, /, /, /, /, /, /, /, /, /, /, /, /, /, /, /, /, /, /, /, /, /, /, /, /, /, /, /, /, /, /, /, /, /, /, /, /, /, /, /, /, /, /, /, /, /
I148: =CONCATENATE("Retenções: ",I140," ","R$ ",K140," ",I141," ","R$ ",K141," ",M140," ","R$ ",O140," ",M141," ","R$ ",O141) -> Retenções: PIS 0,65% R$ 0 COFINS 3% R$ 0 IRRF 1,5% R$ 0 CSLL 1% R$ 0
G150: 10.519.123/0001-97

Sheet 7.02 
C1: FATURAR POR MUNICÍPIO | N1: =SUBTOTAL(9,Parcela1[Coluna1]) -> 10
A2: SP TIM | B2: CÓDIGO FAT | C2: MUNICÍPIO | D2: UF | E2: SITE NAME | F2: OPERADORA | G2: PO | H2: LINE | I2: DU | J2: ItemCode | K2: Preço | L2: Qty | M2: Total | N2: Proporção | O2: Coluna1 | P2: NF | Q2: Data | S2: UF | T2: CC
A3: NE1 | B3: 7.02 | C3: BR_AL_MACEIO_Tax | D3: AL | E3: LOT_AL | F3: VIVO | G3: 6211HG3360340-3062 | H3: 5 | I3: 20250708589335 | J3: 8812441757 | K3: 10 | L3: 1,0000000000 | M3: 10 | N3: 1 | O3: 10
C1079: MÁXIMO DE 25 LINHAS | K1079: 7.02
K1080: TOTAL DA NF | M1080: =SUBTOTAL(9,O2:O1076) -> 10
C1081: PO | D1081: LINE | E1081: ="PO "&C1081&" LINE "&D1081&" " -> PO PO LINE LINE | H1081: MUNICÍPIO | I1081: UF
C1082: 6211HG3360340-2227 | D1082: 3 | E1082: ="PO "&C1082&" LINE "&D1082&" " -> PO 6211HG3360340-2227 LINE 3 | H1082: SANTA CRUZ | I1082: RN | K1082: DEDUÇÃO INSS | L1082: Sim
C1083: 6211HG3360340-2227 | D1083: 4 | E1083: ="PO "&C1083&" LINE "&D1083&" " -> PO 6211HG3360340-2227 LINE 4 | K1083: DEDUÇÃO ISS | L1083: 0 | M1083: COLOCAR PERCENTUAL
C1084: 6211HG3360340-2227 | D1084: 6 | E1084: ="PO "&C1084&" LINE "&D1084&" " -> PO 6211HG3360340-2227 LINE 6 | K1084: MATERIAL | L1084: =L1083 -> 0 | M1084: =IF(L1084=R1075,"0", ROUND(L1084*M1080,2)) -> 0
C1085: 6211HG3360340-2227 | D1085: 1 | E1085: ="PO "&C1085&" LINE "&D1085&" " -> PO 6211HG3360340-2227 LINE 1 | K1085: SERVIÇO | L1085: =IF(L1084="0%",100%,100%-L1084) -> 1 | M1085: =ROUND(L1085*M1080,2) -> 10 | P1085: NAJ
C1086: 6211HG3360340-2227 | D1086: 2 | E1086: ="PO "&C1086&" LINE "&D1086&" " -> PO 6211HG3360340-2227 LINE 2
C1087: 6211HG3360340-2227 | D1087: 5 | E1087: ="PO "&C1087&" LINE "&D1087&" " -> PO 6211HG3360340-2227 LINE 5 | K1087: BASE CALC. ISS | L1087: =IF(L1083="Não",100%,100%-L1083) -> 1 | M1087: =ROUND(L1087*M1080,2) -> 10
K1088: BASE CALC. INSS | L1088: 1 | M1088: =ROUND(L1088*M1080,2) -> 10
K1090: OUTRAS RETENÇÕES | L1090: 0.05 | M1090: =ROUND(L1090*M1087,2) -> 0.5
K1091: RET. INSS | L1091: 0.035 | M1091: =ROUND(L1091*M1088,2) -> 0.35
K1093: Líquido NF | M1093: =M1080-M1090-M1091 -> 9.15
H1095: 10.519.123/0001-97 | K1095: Execução por empreitada de obras de construção civil e elétrica – adequação de infraestrutura, instalação e montagem de equipamentos de rede de telefonia celular, conforme pedidos de compra abaixo:
K1096: =E1082&E1083&E1084&E1085&E1086&E1087&E1088&E1089&E1090&E1091&E1092&E1093&E1094&E1095&E1096&E1097&E1098&E1099&E1100&E1101&E1102&E1103&E1104&E1105&E1106&E1127 -> PO 6211HG3360340-2227 LINE 3 PO 6211HG3360340-2227 LINE 4 PO 6211HG3360340-2227 LINE 6 PO 6211HG3360340-2227 LINE 1 PO 6211HG3360340-2227 LINE 2 PO 6211HG3360340-2227 LINE 5
K1097: =CONCATENATE("Município: "&H1082&" /"&I1082) -> Município: SANTA CRUZ /RN
K1098: =CONCATENATE("Material "&L1084*100&"% - R$ "&M1084&" "&"Serviço "&L1085*100&"% - R$ "&M1085) -> Material 0% - R$ 0 Serviço 100% - R$ 10
K1099: =CONCATENATE("Base de Cálculo ISS - R$ "&M1087&" "&"Base de Cálculo INSS - R$ "&M1088) -> Base de Cálculo ISS - R$ 10 Base de Cálculo INSS - R$ 10
K1100: =CONCATENATE("Retenções ISS "&L1090*100&"%"&" Município: "&H1082&" /"&I1082&" "&" Retenções INSS "&L1091*100&"% ") -> Retenções ISS 5% Município: SANTA CRUZ /RN Retenções INSS 3,5%
K1101: O ISS desta NFS-e será retido pelo tomador de serviço.
J1102: LEGISLAÇÃO | K1102: =IFERROR(IF(H1082="","",VLOOKUP(H1082&" / "&I1082,#REF!,2,FALSE)),"")

Sheet BASE
K1: DIFERENÇA | L1: =M1-RESUMO!C5 -> 1259.028 | M1: =SUM(Tabela6[Valor da Parcela]) -> 1279.028
A3: CC | B3: CÓDIGO FAT | C3: MUNICÍPIO | D3: UF | E3: SITE NAME | F3: OPERADORA | G3: PO | H3: LINE | I3: DU | J3: ItemCode | K3: Preço | L3: Qty | M3: Total | N3: Proporção | O3: Valor da Parcela
A4: =IF(VLOOKUP(Tabela6[[#This Row],[UF]],'BASE CC'!B:C,2,0)="SP",IF(Tabela6[[#This Row],[OPERADORA]]="TIM","SP TIM","SPI"),VLOOKUP(Tabela6[[#This Row],[UF]],'BASE CC'!B:C,2,0)) -> NE2 | B4: =VLOOKUP(Tabela_Base_Financeiro[[#This Row],[Item code]],'COD.FAT'!B:C,2,0) -> 7.03 | C4: =Tabela_Base_Financeiro[[#This Row],[PO Ship TO]] -> BR_CE_AQUIRAZ_Tax | D4: =RIGHT(Tabela_Base_Financeiro[[#This Row],[Manufacturer]],2) -> CE | E4: =IF(VLOOKUP(Tabela_Base_Financeiro[[#This Row],[Project Code]],'COD. PROJETOS'!B:D,3,0)="VIVO",MID(Tabela_Base_Financeiro[[#This Row],[Manufacturer]],36,6),IF(VLOOKUP(Tabela_Base_Financeiro[[#This Row],[Project Code]],'COD. PROJETOS'!B:D,3,0)="CLARO",MID(Tabela_Base_Financeiro[[#This Row],[Manufacturer]],36,7),IF(VLOOKUP(Tabela_Base_Financeiro[[#This Row],[Project Code]],'COD. PROJETOS'!B:D,3,0)="TIM",MID(Tabela_Base_Financeiro[[#This Row],[Manufacturer]],36,9),"PROJETO?"))) -> CEAQU07 | F4: =VLOOKUP(Tabela_Base_Financeiro[[#This Row],[Project Code]],'COD. PROJETOS'!B:D,3,0) -> CLARO | G4: =IFERROR(Tabela_Base_Financeiro[[#This Row],[PO No,]],0) -> 6211HG3360340-1482 | H4: =IFERROR(Tabela_Base_Financeiro[[#This Row],[Line No,]],0) -> 1 | I4: =IFERROR(MID(Tabela_Base_Financeiro[[#This Row],[Manufacturer]],19,14),"") -> 20250326476411 | J4: =IFERROR(Tabela_Base_Financeiro[[#This Row],[Item code]],0) -> 8812441617 | K4: =IFERROR(Tabela_Base_Financeiro[[#This Row],[Unit Price]],0) -> 1240,5 | L4: =IFERROR(Tabela_Base_Financeiro[[#This Row],[AC Qty,]],0) -> 1,0000000000 | M4: =Tabela6[[#This Row],[Qty]]*Tabela6[[#This Row],[Preço]] -> 1240.5 | N4: =IFERROR(Tabela_Base_Financeiro[[#This Row],[Proportion]],0) -> 1 | O4: =Tabela6[[#This Row],[Proporção]]*Tabela6[[#This Row],[Total]] -> 1240.5
A5: =IF(VLOOKUP(Tabela6[[#This Row],[UF]],'BASE CC'!B:C,2,0)="SP",IF(Tabela6[[#This Row],[OPERADORA]]="TIM","SP TIM","SPI"),VLOOKUP(Tabela6[[#This Row],[UF]],'BASE CC'!B:C,2,0)) -> NE1 | B5: =VLOOKUP(Tabela_Base_Financeiro[[#This Row],[Item code]],'COD.FAT'!B:C,2,0) -> 7.02 | C5: =Tabela_Base_Financeiro[[#This Row],[PO Ship TO]] -> BR_AL_MACEIO_Tax | D5: =RIGHT(Tabela_Base_Financeiro[[#This Row],[Manufacturer]],2) -> AL | E5: =IF(VLOOKUP(Tabela_Base_Financeiro[[#This Row],[Project Code]],'COD. PROJETOS'!B:D,3,0)="VIVO",MID(Tabela_Base_Financeiro[[#This Row],[Manufacturer]],36,6),IF(VLOOKUP(Tabela_Base_Financeiro[[#This Row],[Project Code]],'COD. PROJETOS'!B:D,3,0)="CLARO",MID(Tabela_Base_Financeiro[[#This Row],[Manufacturer]],36,7),IF(VLOOKUP(Tabela_Base_Financeiro[[#This Row],[Project Code]],'COD. PROJETOS'!B:D,3,0)="TIM",MID(Tabela_Base_Financeiro[[#This Row],[Manufacturer]],36,9),"PROJETO?"))) -> LOT_AL | F5: =VLOOKUP(Tabela_Base_Financeiro[[#This Row],[Project Code]],'COD. PROJETOS'!B:D,3,0) -> VIVO | G5: =IFERROR(Tabela_Base_Financeiro[[#This Row],[PO No,]],0) -> 6211HG3360340-3062 | H5: =IFERROR(Tabela_Base_Financeiro[[#This Row],[Line No,]],0) -> 5 | I5: =IFERROR(MID(Tabela_Base_Financeiro[[#This Row],[Manufacturer]],19,14),"") -> 20250708589335 | J5: =IFERROR(Tabela_Base_Financeiro[[#This Row],[Item code]],0) -> 8812441757 | K5: =IFERROR(Tabela_Base_Financeiro[[#This Row],[Unit Price]],0) -> 38,528 | L5: =IFERROR(Tabela_Base_Financeiro[[#This Row],[AC Qty,]],0) -> 1,0000000000 | M5: =Tabela6[[#This Row],[Qty]]*Tabela6[[#This Row],[Preço]] -> 38.528 | N5: =IFERROR(Tabela_Base_Financeiro[[#This Row],[Proportion]],0) -> 1 | O5: =Tabela6[[#This Row],[Proporção]]*Tabela6[[#This Row],[Total]] -> 38.528
A6: =IF(VLOOKUP(Tabela6[[#This Row],[UF]],'BASE CC'!B:C,2,0)="SP",IF(Tabela6[[#This Row],[OPERADORA]]="TIM","SP TIM","SPI"),VLOOKUP(Tabela6[[#This Row],[UF]],'BASE CC'!B:C,2,0)) -> #N/A | B6: =VLOOKUP(Tabela_Base_Financeiro[[#This Row],[Item code]],'COD.FAT'!B:C,2,0) -> #N/A | C6: =Tabela_Base_Financeiro[[#This Row],[PO Ship TO]] -> 0 | D6: =RIGHT(Tabela_Base_Financeiro[[#This Row],[Manufacturer]],2) | E6: =IF(VLOOKUP(Tabela_Base_Financeiro[[#This Row],[Project Code]],'COD. PROJETOS'!B:D,3,0)="VIVO",MID(Tabela_Base_Financeiro[[#This Row],[Manufacturer]],36,6),IF(VLOOKUP(Tabela_Base_Financeiro[[#This Row],[Project Code]],'COD. PROJETOS'!B:D,3,0)="CLARO",MID(Tabela_Base_Financeiro[[#This Row],[Manufacturer]],36,7),IF(VLOOKUP(Tabela_Base_Financeiro[[#This Row],[Project Code]],'COD. PROJETOS'!B:D,3,0)="TIM",MID(Tabela_Base_Financeiro[[#This Row],[Manufacturer]],36,9),"PROJETO?"))) -> #N/A | F6: =VLOOKUP(Tabela_Base_Financeiro[[#This Row],[Project Code]],'COD. PROJETOS'!B:D,3,0) -> #N/A | G6: =IFERROR(Tabela_Base_Financeiro[[#This Row],[PO No,]],0) -> 0 | H6: =IFERROR(Tabela_Base_Financeiro[[#This Row],[Line No,]],0) -> 0 | I6: =IFERROR(MID(Tabela_Base_Financeiro[[#This Row],[Manufacturer]],19,14),"") | J6: =IFERROR(Tabela_Base_Financeiro[[#This Row],[Item code]],0) -> 0 | K6: =IFERROR(Tabela_Base_Financeiro[[#This Row],[Unit Price]],0) -> 0 | L6: =IFERROR(Tabela_Base_Financeiro[[#This Row],[AC Qty,]],0) -> 0 | M6: =Tabela6[[#This Row],[Qty]]*Tabela6[[#This Row],[Preço]] -> 0 | N6: =IFERROR(Tabela_Base_Financeiro[[#This Row],[Proportion]],0) -> 0 | O6: =Tabela6[[#This Row],[Proporção]]*Tabela6[[#This Row],[Total]] -> 0
A7: =IF(VLOOKUP(Tabela6[[#This Row],[UF]],'BASE CC'!B:C,2,0)="SP",IF(Tabela6[[#This Row],[OPERADORA]]="TIM","SP TIM","SPI"),VLOOKUP(Tabela6[[#This Row],[UF]],'BASE CC'!B:C,2,0)) -> #N/A | B7: =VLOOKUP(Tabela_Base_Financeiro[[#This Row],[Item code]],'COD.FAT'!B:C,2,0) -> #N/A | C7: =Tabela_Base_Financeiro[[#This Row],[PO Ship TO]] -> 0 | D7: =RIGHT(Tabela_Base_Financeiro[[#This Row],[Manufacturer]],2) | E7: =IF(VLOOKUP(Tabela_Base_Financeiro[[#This Row],[Project Code]],'COD. PROJETOS'!B:D,3,0)="VIVO",MID(Tabela_Base_Financeiro[[#This Row],[Manufacturer]],36,6),IF(VLOOKUP(Tabela_Base_Financeiro[[#This Row],[Project Code]],'COD. PROJETOS'!B:D,3,0)="CLARO",MID(Tabela_Base_Financeiro[[#This Row],[Manufacturer]],36,7),IF(VLOOKUP(Tabela_Base_Financeiro[[#This Row],[Project Code]],'COD. PROJETOS'!B:D,3,0)="TIM",MID(Tabela_Base_Financeiro[[#This Row],[Manufacturer]],36,9),"PROJETO?"))) -> #N/A | F7: =VLOOKUP(Tabela_Base_Financeiro[[#This Row],[Project Code]],'COD. PROJETOS'!B:D,3,0) -> #N/A | G7: =IFERROR(Tabela_Base_Financeiro[[#This Row],[PO No,]],0) -> 0 | H7: =IFERROR(Tabela_Base_Financeiro[[#This Row],[Line No,]],0) -> 0 | I7: =IFERROR(MID(Tabela_Base_Financeiro[[#This Row],[Manufacturer]],19,14),"") | J7: =IFERROR(Tabela_Base_Financeiro[[#This Row],[Item code]],0) -> 0 | K7: =IFERROR(Tabela_Base_Financeiro[[#This Row],[Unit Price]],0) -> 0 | L7: =IFERROR(Tabela_Base_Financeiro[[#This Row],[AC Qty,]],0) -> 0 | M7: =Tabela6[[#This Row],[Qty]]*Tabela6[[#This Row],[Preço]] -> 0 | N7: =IFERROR(Tabela_Base_Financeiro[[#This Row],[Proportion]],0) -> 0 | O7: =Tabela6[[#This Row],[Proporção]]*Tabela6[[#This Row],[Total]] -> 0
A8: =IF(VLOOKUP(Tabela6[[#This Row],[UF]],'BASE CC'!B:C,2,0)="SP",IF(Tabela6[[#This Row],[OPERADORA]]="TIM","SP TIM","SPI"),VLOOKUP(Tabela6[[#This Row],[UF]],'BASE CC'!B:C,2,0)) -> #N/A | B8: =VLOOKUP(Tabela_Base_Financeiro[[#This Row],[Item code]],'COD.FAT'!B:C,2,0) -> #N/A | C8: =Tabela_Base_Financeiro[[#This Row],[PO Ship TO]] -> 0 | D8: =RIGHT(Tabela_Base_Financeiro[[#This Row],[Manufacturer]],2) | E8: =IF(VLOOKUP(Tabela_Base_Financeiro[[#This Row],[Project Code]],'COD. PROJETOS'!B:D,3,0)="VIVO",MID(Tabela_Base_Financeiro[[#This Row],[Manufacturer]],36,6),IF(VLOOKUP(Tabela_Base_Financeiro[[#This Row],[Project Code]],'COD. PROJETOS'!B:D,3,0)="CLARO",MID(Tabela_Base_Financeiro[[#This Row],[Manufacturer]],36,7),IF(VLOOKUP(Tabela_Base_Financeiro[[#This Row],[Project Code]],'COD. PROJETOS'!B:D,3,0)="TIM",MID(Tabela_Base_Financeiro[[#This Row],[Manufacturer]],36,9),"PROJETO?"))) -> #N/A | F8: =VLOOKUP(Tabela_Base_Financeiro[[#This Row],[Project Code]],'COD. PROJETOS'!B:D,3,0) -> #N/A | G8: =IFERROR(Tabela_Base_Financeiro[[#This Row],[PO No,]],0) -> 0 | H8: =IFERROR(Tabela_Base_Financeiro[[#This Row],[Line No,]],0) -> 0 | I8: =IFERROR(MID(Tabela_Base_Financeiro[[#This Row],[Manufacturer]],19,14),"") | J8: =IFERROR(Tabela_Base_Financeiro[[#This Row],[Item code]],0) -> 0 | K8: =IFERROR(Tabela_Base_Financeiro[[#This Row],[Unit Price]],0) -> 0 | L8: =IFERROR(Tabela_Base_Financeiro[[#This Row],[AC Qty,]],0) -> 0 | M8: =Tabela6[[#This Row],[Qty]]*Tabela6[[#This Row],[Preço]] -> 0 | N8: =IFERROR(Tabela_Base_Financeiro[[#This Row],[Proportion]],0) -> 0 | O8: =Tabela6[[#This Row],[Proporção]]*Tabela6[[#This Row],[Total]] -> 0
A9: =IF(VLOOKUP(Tabela6[[#This Row],[UF]],'BASE CC'!B:C,2,0)="SP",IF(Tabela6[[#This Row],[OPERADORA]]="TIM","SP TIM","SPI"),VLOOKUP(Tabela6[[#This Row],[UF]],'BASE CC'!B:C,2,0)) -> #N/A | B9: =VLOOKUP(Tabela_Base_Financeiro[[#This Row],[Item code]],'COD.FAT'!B:C,2,0) -> #N/A | C9: =Tabela_Base_Financeiro[[#This Row],[PO Ship TO]] -> 0 | D9: =RIGHT(Tabela_Base_Financeiro[[#This Row],[Manufacturer]],2) | E9: =IF(VLOOKUP(Tabela_Base_Financeiro[[#This Row],[Project Code]],'COD. PROJETOS'!B:D,3,0)="VIVO",MID(Tabela_Base_Financeiro[[#This Row],[Manufacturer]],36,6),IF(VLOOKUP(Tabela_Base_Financeiro[[#This Row],[Project Code]],'COD. PROJETOS'!B:D,3,0)="CLARO",MID(Tabela_Base_Financeiro[[#This Row],[Manufacturer]],36,7),IF(VLOOKUP(Tabela_Base_Financeiro[[#This Row],[Project Code]],'COD. PROJETOS'!B:D,3,0)="TIM",MID(Tabela_Base_Financeiro[[#This Row],[Manufacturer]],36,9),"PROJETO?"))) -> #N/A | F9: =VLOOKUP(Tabela_Base_Financeiro[[#This Row],[Project Code]],'COD. PROJETOS'!B:D,3,0) -> #N/A | G9: =IFERROR(Tabela_Base_Financeiro[[#This Row],[PO No,]],0) -> 0 | H9: =IFERROR(Tabela_Base_Financeiro[[#This Row],[Line No,]],0) -> 0 | I9: =IFERROR(MID(Tabela_Base_Financeiro[[#This Row],[Manufacturer]],19,14),"") | J9: =IFERROR(Tabela_Base_Financeiro[[#This Row],[Item code]],0) -> 0 | K9: =IFERROR(Tabela_Base_Financeiro[[#This Row],[Unit Price]],0) -> 0 | L9: =IFERROR(Tabela_Base_Financeiro[[#This Row],[AC Qty,]],0) -> 0 | M9: =Tabela6[[#This Row],[Qty]]*Tabela6[[#This Row],[Preço]] -> 0 | N9: =IFERROR(Tabela_Base_Financeiro[[#This Row],[Proportion]],0) -> 0 | O9: =Tabela6[[#This Row],[Proporção]]*Tabela6[[#This Row],[Total]] -> 0
A10: =IF(VLOOKUP(Tabela6[[#This Row],[UF]],'BASE CC'!B:C,2,0)="SP",IF(Tabela6[[#This Row],[OPERADORA]]="TIM","SP TIM","SPI"),VLOOKUP(Tabela6[[#This Row],[UF]],'BASE CC'!B:C,2,0)) -> #N/A | B10: =VLOOKUP(Tabela_Base_Financeiro[[#This Row],[Item code]],'COD.FAT'!B:C,2,0) -> #N/A | C10: =Tabela_Base_Financeiro[[#This Row],[PO Ship TO]] -> 0 | D10: =RIGHT(Tabela_Base_Financeiro[[#This Row],[Manufacturer]],2) | E10: =IF(VLOOKUP(Tabela_Base_Financeiro[[#This Row],[Project Code]],'COD. PROJETOS'!B:D,3,0)="VIVO",MID(Tabela_Base_Financeiro[[#This Row],[Manufacturer]],36,6),IF(VLOOKUP(Tabela_Base_Financeiro[[#This Row],[Project Code]],'COD. PROJETOS'!B:D,3,0)="CLARO",MID(Tabela_Base_Financeiro[[#This Row],[Manufacturer]],36,7),IF(VLOOKUP(Tabela_Base_Financeiro[[#This Row],[Project Code]],'COD. PROJETOS'!B:D,3,0)="TIM",MID(Tabela_Base_Financeiro[[#This Row],[Manufacturer]],36,9),"PROJETO?"))) -> #N/A | F10: =VLOOKUP(Tabela_Base_Financeiro[[#This Row],[Project Code]],'COD. PROJETOS'!B:D,3,0) -> #N/A | G10: =IFERROR(Tabela_Base_Financeiro[[#This Row],[PO No,]],0) -> 0 | H10: =IFERROR(Tabela_Base_Financeiro[[#This Row],[Line No,]],0) -> 0 | I10: =IFERROR(MID(Tabela_Base_Financeiro[[#This Row],[Manufacturer]],19,14),"") | J10: =IFERROR(Tabela_Base_Financeiro[[#This Row],[Item code]],0) -> 0 | K10: =IFERROR(Tabela_Base_Financeiro[[#This Row],[Unit Price]],0) -> 0 | L10: =IFERROR(Tabela_Base_Financeiro[[#This Row],[AC Qty,]],0) -> 0 | M10: =Tabela6[[#This Row],[Qty]]*Tabela6[[#This Row],[Preço]] -> 0 | N10: =IFERROR(Tabela_Base_Financeiro[[#This Row],[Proportion]],0) -> 0 | O10: =Tabela6[[#This Row],[Proporção]]*Tabela6[[#This Row],[Total]] -> 0
A11: =IF(VLOOKUP(Tabela6[[#This Row],[UF]],'BASE CC'!B:C,2,0)="SP",IF(Tabela6[[#This Row],[OPERADORA]]="TIM","SP TIM","SPI"),VLOOKUP(Tabela6[[#This Row],[UF]],'BASE CC'!B:C,2,0)) -> #N/A | B11: =VLOOKUP(Tabela_Base_Financeiro[[#This Row],[Item code]],'COD.FAT'!B:C,2,0) -> #N/A | C11: =Tabela_Base_Financeiro[[#This Row],[PO Ship TO]] -> 0 | D11: =RIGHT(Tabela_Base_Financeiro[[#This Row],[Manufacturer]],2) | E11: =IF(VLOOKUP(Tabela_Base_Financeiro[[#This Row],[Project Code]],'COD. PROJETOS'!B:D,3,0)="VIVO",MID(Tabela_Base_Financeiro[[#This Row],[Manufacturer]],36,6),IF(VLOOKUP(Tabela_Base_Financeiro[[#This Row],[Project Code]],'COD. PROJETOS'!B:D,3,0)="CLARO",MID(Tabela_Base_Financeiro[[#This Row],[Manufacturer]],36,7),IF(VLOOKUP(Tabela_Base_Financeiro[[#This Row],[Project Code]],'COD. PROJETOS'!B:D,3,0)="TIM",MID(Tabela_Base_Financeiro[[#This Row],[Manufacturer]],36,9),"PROJETO?"))) -> #N/A | F11: =VLOOKUP(Tabela_Base_Financeiro[[#This Row],[Project Code]],'COD. PROJETOS'!B:D,3,0) -> #N/A | G11: =IFERROR(Tabela_Base_Financeiro[[#This Row],[PO No,]],0) -> 0 | H11: =IFERROR(Tabela_Base_Financeiro[[#This Row],[Line No,]],0) -> 0 | I11: =IFERROR(MID(Tabela_Base_Financeiro[[#This Row],[Manufacturer]],19,14),"") | J11: =IFERROR(Tabela_Base_Financeiro[[#This Row],[Item code]],0) -> 0 | K11: =IFERROR(Tabela_Base_Financeiro[[#This Row],[Unit Price]],0) -> 0 | L11: =IFERROR(Tabela_Base_Financeiro[[#This Row],[AC Qty,]],0) -> 0 | M11: =Tabela6[[#This Row],[Qty]]*Tabela6[[#This Row],[Preço]] -> 0 | N11: =IFERROR(Tabela_Base_Financeiro[[#This Row],[Proportion]],0) -> 0 | O11: =Tabela6[[#This Row],[Proporção]]*Tabela6[[#This Row],[Total]] -> 0
A12: =IF(VLOOKUP(Tabela6[[#This Row],[UF]],'BASE CC'!B:C,2,0)="SP",IF(Tabela6[[#This Row],[OPERADORA]]="TIM","SP TIM","SPI"),VLOOKUP(Tabela6[[#This Row],[UF]],'BASE CC'!B:C,2,0)) -> #N/A | B12: =VLOOKUP(Tabela_Base_Financeiro[[#This Row],[Item code]],'COD.FAT'!B:C,2,0) -> #N/A | C12: =Tabela_Base_Financeiro[[#This Row],[PO Ship TO]] -> 0 | D12: =RIGHT(Tabela_Base_Financeiro[[#This Row],[Manufacturer]],2) | E12: =IF(VLOOKUP(Tabela_Base_Financeiro[[#This Row],[Project Code]],'COD. PROJETOS'!B:D,3,0)="VIVO",MID(Tabela_Base_Financeiro[[#This Row],[Manufacturer]],36,6),IF(VLOOKUP(Tabela_Base_Financeiro[[#This Row],[Project Code]],'COD. PROJETOS'!B:D,3,0)="CLARO",MID(Tabela_Base_Financeiro[[#This Row],[Manufacturer]],36,7),IF(VLOOKUP(Tabela_Base_Financeiro[[#This Row],[Project Code]],'COD. PROJETOS'!B:D,3,0)="TIM",MID(Tabela_Base_Financeiro[[#This Row],[Manufacturer]],36,9),"PROJETO?"))) -> #N/A | F12: =VLOOKUP(Tabela_Base_Financeiro[[#This Row],[Project Code]],'COD. PROJETOS'!B:D,3,0) -> #N/A | G12: =IFERROR(Tabela_Base_Financeiro[[#This Row],[PO No,]],0) -> 0 | H12: =IFERROR(Tabela_Base_Financeiro[[#This Row],[Line No,]],0) -> 0 | I12: =IFERROR(MID(Tabela_Base_Financeiro[[#This Row],[Manufacturer]],19,14),"") | J12: =IFERROR(Tabela_Base_Financeiro[[#This Row],[Item code]],0) -> 0 | K12: =IFERROR(Tabela_Base_Financeiro[[#This Row],[Unit Price]],0) -> 0 | L12: =IFERROR(Tabela_Base_Financeiro[[#This Row],[AC Qty,]],0) -> 0 | M12: =Tabela6[[#This Row],[Qty]]*Tabela6[[#This Row],[Preço]] -> 0 | N12: =IFERROR(Tabela_Base_Financeiro[[#This Row],[Proportion]],0) -> 0 | O12: =Tabela6[[#This Row],[Proporção]]*Tabela6[[#This Row],[Total]] -> 0
A13: =IF(VLOOKUP(Tabela6[[#This Row],[UF]],'BASE CC'!B:C,2,0)="SP",IF(Tabela6[[#This Row],[OPERADORA]]="TIM","SP TIM","SPI"),VLOOKUP(Tabela6[[#This Row],[UF]],'BASE CC'!B:C,2,0)) -> #N/A | B13: =VLOOKUP(Tabela_Base_Financeiro[[#This Row],[Item code]],'COD.FAT'!B:C,2,0) -> #N/A | C13: =Tabela_Base_Financeiro[[#This Row],[PO Ship TO]] -> 0 | D13: =RIGHT(Tabela_Base_Financeiro[[#This Row],[Manufacturer]],2) | E13: =IF(VLOOKUP(Tabela_Base_Financeiro[[#This Row],[Project Code]],'COD. PROJETOS'!B:D,3,0)="VIVO",MID(Tabela_Base_Financeiro[[#This Row],[Manufacturer]],36,6),IF(VLOOKUP(Tabela_Base_Financeiro[[#This Row],[Project Code]],'COD. PROJETOS'!B:D,3,0)="CLARO",MID(Tabela_Base_Financeiro[[#This Row],[Manufacturer]],36,7),IF(VLOOKUP(Tabela_Base_Financeiro[[#This Row],[Project Code]],'COD. PROJETOS'!B:D,3,0)="TIM",MID(Tabela_Base_Financeiro[[#This Row],[Manufacturer]],36,9),"PROJETO?"))) -> #N/A | F13: =VLOOKUP(Tabela_Base_Financeiro[[#This Row],[Project Code]],'COD. PROJETOS'!B:D,3,0) -> #N/A | G13: =IFERROR(Tabela_Base_Financeiro[[#This Row],[PO No,]],0) -> 0 | H13: =IFERROR(Tabela_Base_Financeiro[[#This Row],[Line No,]],0) -> 0 | I13: =IFERROR(MID(Tabela_Base_Financeiro[[#This Row],[Manufacturer]],19,14),"") | J13: =IFERROR(Tabela_Base_Financeiro[[#This Row],[Item code]],0) -> 0 | K13: =IFERROR(Tabela_Base_Financeiro[[#This Row],[Unit Price]],0) -> 0 | L13: =IFERROR(Tabela_Base_Financeiro[[#This Row],[AC Qty,]],0) -> 0 | M13: =Tabela6[[#This Row],[Qty]]*Tabela6[[#This Row],[Preço]] -> 0 | N13: =IFERROR(Tabela_Base_Financeiro[[#This Row],[Proportion]],0) -> 0 | O13: =Tabela6[[#This Row],[Proporção]]*Tabela6[[#This Row],[Total]] -> 0
A14: =IF(VLOOKUP(Tabela6[[#This Row],[UF]],'BASE CC'!B:C,2,0)="SP",IF(Tabela6[[#This Row],[OPERADORA]]="TIM","SP TIM","SPI"),VLOOKUP(Tabela6[[#This Row],[UF]],'BASE CC'!B:C,2,0)) -> #N/A | B14: =VLOOKUP(Tabela_Base_Financeiro[[#This Row],[Item code]],'COD.FAT'!B:C,2,0) -> #N/A | C14: =Tabela_Base_Financeiro[[#This Row],[PO Ship TO]] -> 0 | D14: =RIGHT(Tabela_Base_Financeiro[[#This Row],[Manufacturer]],2) | E14: =IF(VLOOKUP(Tabela_Base_Financeiro[[#This Row],[Project Code]],'COD. PROJETOS'!B:D,3,0)="VIVO",MID(Tabela_Base_Financeiro[[#This Row],[Manufacturer]],36,6),IF(VLOOKUP(Tabela_Base_Financeiro[[#This Row],[Project Code]],'COD. PROJETOS'!B:D,3,0)="CLARO",MID(Tabela_Base_Financeiro[[#This Row],[Manufacturer]],36,7),IF(VLOOKUP(Tabela_Base_Financeiro[[#This Row],[Project Code]],'COD. PROJETOS'!B:D,3,0)="TIM",MID(Tabela_Base_Financeiro[[#This Row],[Manufacturer]],36,9),"PROJETO?"))) -> #N/A | F14: =VLOOKUP(Tabela_Base_Financeiro[[#This Row],[Project Code]],'COD. PROJETOS'!B:D,3,0) -> #N/A | G14: =IFERROR(Tabela_Base_Financeiro[[#This Row],[PO No,]],0) -> 0 | H14: =IFERROR(Tabela_Base_Financeiro[[#This Row],[Line No,]],0) -> 0 | I14: =IFERROR(MID(Tabela_Base_Financeiro[[#This Row],[Manufacturer]],19,14),"") | J14: =IFERROR(Tabela_Base_Financeiro[[#This Row],[Item code]],0) -> 0 | K14: =IFERROR(Tabela_Base_Financeiro[[#This Row],[Unit Price]],0) -> 0 | L14: =IFERROR(Tabela_Base_Financeiro[[#This Row],[AC Qty,]],0) -> 0 | M14: =Tabela6[[#This Row],[Qty]]*Tabela6[[#This Row],[Preço]] -> 0 | N14: =IFERROR(Tabela_Base_Financeiro[[#This Row],[Proportion]],0) -> 0 | O14: =Tabela6[[#This Row],[Proporção]]*Tabela6[[#This Row],[Total]] -> 0
A15: =IF(VLOOKUP(Tabela6[[#This Row],[UF]],'BASE CC'!B:C,2,0)="SP",IF(Tabela6[[#This Row],[OPERADORA]]="TIM","SP TIM","SPI"),VLOOKUP(Tabela6[[#This Row],[UF]],'BASE CC'!B:C,2,0)) -> #N/A | B15: =VLOOKUP(Tabela_Base_Financeiro[[#This Row],[Item code]],'COD.FAT'!B:C,2,0) -> #N/A | C15: =Tabela_Base_Financeiro[[#This Row],[PO Ship TO]] -> 0 | D15: =RIGHT(Tabela_Base_Financeiro[[#This Row],[Manufacturer]],2) | E15: =IF(VLOOKUP(Tabela_Base_Financeiro[[#This Row],[Project Code]],'COD. PROJETOS'!B:D,3,0)="VIVO",MID(Tabela_Base_Financeiro[[#This Row],[Manufacturer]],36,6),IF(VLOOKUP(Tabela_Base_Financeiro[[#This Row],[Project Code]],'COD. PROJETOS'!B:D,3,0)="CLARO",MID(Tabela_Base_Financeiro[[#This Row],[Manufacturer]],36,7),IF(VLOOKUP(Tabela_Base_Financeiro[[#This Row],[Project Code]],'COD. PROJETOS'!B:D,3,0)="TIM",MID(Tabela_Base_Financeiro[[#This Row],[Manufacturer]],36,9),"PROJETO?"))) -> #N/A | F15: =VLOOKUP(Tabela_Base_Financeiro[[#This Row],[Project Code]],'COD. PROJETOS'!B:D,3,0) -> #N/A | G15: =IFERROR(Tabela_Base_Financeiro[[#This Row],[PO No,]],0) -> 0 | H15: =IFERROR(Tabela_Base_Financeiro[[#This Row],[Line No,]],0) -> 0 | I15: =IFERROR(MID(Tabela_Base_Financeiro[[#This Row],[Manufacturer]],19,14),"") | J15: =IFERROR(Tabela_Base_Financeiro[[#This Row],[Item code]],0) -> 0 | K15: =IFERROR(Tabela_Base_Financeiro[[#This Row],[Unit Price]],0) -> 0 | L15: =IFERROR(Tabela_Base_Financeiro[[#This Row],[AC Qty,]],0) -> 0 | M15: =Tabela6[[#This Row],[Qty]]*Tabela6[[#This Row],[Preço]] -> 0 | N15: =IFERROR(Tabela_Base_Financeiro[[#This Row],[Proportion]],0) -> 0 | O15: =Tabela6[[#This Row],[Proporção]]*Tabela6[[#This Row],[Total]] -> 0
... A1119: =IF(VLOOKUP(Tabela6[[#This Row],[UF]],'BASE CC'!B:C,2,0)="SP",IF(Tabela6[[#This Row],[OPERADORA]]="TIM","SP TIM","SPI"),VLOOKUP(Tabela6[[#This Row],[UF]],'BASE CC'!B:C,2,0)) -> #VALUE! | B1119: =VLOOKUP(Tabela_Base_Financeiro[[#This Row],[Item code]],'COD.FAT'!B:C,2,0) -> #VALUE! | C1119: =Tabela_Base_Financeiro[[#This Row],[PO Ship TO]] -> #VALUE! | D1119: =RIGHT(Tabela_Base_Financeiro[[#This Row],[Manufacturer]],2) -> #VALUE! | E1119: =IF(VLOOKUP(Tabela_Base_Financeiro[[#This Row],[Project Code]],'COD. PROJETOS'!B:D,3,0)="VIVO",MID(Tabela_Base_Financeiro[[#This Row],[Manufacturer]],36,6),IF(VLOOKUP(Tabela_Base_Financeiro[[#This Row],[Project Code]],'COD. PROJETOS'!B:D,3,0)="CLARO",MID(Tabela_Base_Financeiro[[#This Row],[Manufacturer]],36,7),IF(VLOOKUP(Tabela_Base_Financeiro[[#This Row],[Project Code]],'COD. PROJETOS'!B:D,3,0)="TIM",MID(Tabela_Base_Financeiro[[#This Row],[Manufacturer]],36,9),"PROJETO?"))) -> #VALUE! | F1119: =VLOOKUP(Tabela_Base_Financeiro[[#This Row],[Project Code]],'COD. PROJETOS'!B:D,3,0) -> #VALUE! | G1119: =IFERROR(Tabela_Base_Financeiro[[#This Row],[PO No,]],0) -> 0 | H1119: =IFERROR(Tabela_Base_Financeiro[[#This Row],[Line No,]],0) -> 0 | I1119: =IFERROR(MID(Tabela_Base_Financeiro[[#This Row],[Manufacturer]],19,14),"") | J1119: =IFERROR(Tabela_Base_Financeiro[[#This Row],[Item code]],0) -> 0 | K1119: =IFERROR(Tabela_Base_Financeiro[[#This Row],[Unit Price]],0) -> 0 | L1119: =IFERROR(Tabela_Base_Financeiro[[#This Row],[AC Qty,]],0) -> 0 | M1119: =Tabela6[[#This Row],[Qty]]*Tabela6[[#This Row],[Preço]] -> 0 | N1119: =IFERROR(Tabela_Base_Financeiro[[#This Row],[Proportion]],0) -> 0 | O1119: =Tabela6[[#This Row],[Proporção]]*Tabela6[[#This Row],[Total]] -> 0

Sheet BASE FINANCEIRO
X1: X | AK1: X | AL1: X | AW1: X | BB1: X | BC1: X | BH1: X | BI1: X | CM1: =SUM(Tabela_Base_Financeiro[TOTAL]) -> 0
A3: Customer | B3: poLineLocationId | C3: vendorCode | D3: vendorId | E3: Companycode | F3: poHeadId | G3: poReleaseId | H3: polineId | I3: vendorSiteId | J3: termsId | K3: milestoneId | L3: digestCode | M3: invOrgId | N3: attribute2 | O3: poSource | P3: Location | Q3: CNPJ | R3: PO No, | S3: Release No, | T3: Line No, | U3: Shipment No, | V3: PO Type | W3: PO Qty | X3: AC Qty, | Y3: Billed Qty | Z3: offsetQty | AA3: Unbilled Qty, | AB3: Currency | AC3: shipToLocationId | AD3: Coluna1 | AE3: Coluna2 | AF3: Coluna3 | AG3: Coluna4 | AH3: Coluna5 | AI3: Coluna6 | AJ3: Coluna7 | AK3: Unit Price | AL3: LC Code | AM3: ISS Tax Type | AN3: ISS Rate | AO3: INSS Base Rate | AP3: INSS Rate | AQ3: IRRF Rate | AR3: PCC Rate | AS3: Terms Date Rule | AT3: Terms | AU3: site | AV3: Acceptance Milestone | AW3: Proportion | AX3: Description | AY3: Payment Type | AZ3: payment terms | BA3: Payment Method | BB3: Item code | BC3: Project Code | BD3: Project Name | BE3: Sub Contract No, | BF3: Sales Contract No, | BG3: UOM | BH3: PO Ship TO | BI3: Manufacturer | BJ3: Billing* | BK3: Invoice Type(Brazil) | BL3: DOC_Fiscal | BM3: Series | BN3: Invoice No* | BO3: Invoice Date* | BP3: Invoice Amount (Incl, Tax)* | BQ3: Invoice Key | BR3: BR BarCode | BS3: ICMS type | BT3: ICMS Base | BU3: ICMS Amount | BV3: ICMS ST Base | BW3: ICMS ST Amount | BX3: IPI Base | BY3: IPI Amount | BZ3: ISS_City | CA3: ISS_State | CB3: ISS_Base | CC3: Service_Code | CD3: Iss_Type | CE3: INSS_Base | CF3: INSS_Tax | CG3: IR_Type | CH3: IR_Categ | CI3: IR_Base | CJ3: IR_Rate | CK3: AWT_Group | CL3: remark | CM3: TOTAL
A4: Huawei Gestao e Servicos de Telecomunicacoes do Brasil Ltda, | B4: 1694297958383198214 | C4: AZ0149 | D4: 319275 | E4: 6211 | F4: 1694297958383198210 | H4: 1694297958383198212 | I4: 1701733 | J4: 500001 | L4: 240c4b46725f733536c9d490f21514ff35dbe39ae238f4a75d24c22d4ecea5a6 | M4: BM1 | O4: SERVICE_PROCUREMENT | P4: BM1_Financial | Q4: 10519123000197 | R4: 6211HG3360340-1482 | T4: 1 | U4: 1 | V4: SERVICE_PROCUREMENT | W4: 1 | X4: 1,0000000000 | Y4: 0 | Z4: 0 | AA4: 1 | AB4: BRL | AC4: 3000000795 | AD4: N | AK4: 1240,5 | AL4: 7,03 ELABORACAO PROJETOS | AT4: Pay On Agreement | AU4: BRA | AV4: AC1 | AW4: 1 | AX4: Additional site visit of installation team because of Huawei problem, per site | AZ4: 【TT】▍AC1 (100,00%, INV AC -30D, Complete 100%) ▍ | BB4: 8812441617 | BC4: 56A0CP2 | BE4: FPAMULTBRA25032510450326B1 | BF4: 00A07725169320 | BG4: SITE | BH4: BR_CE_AQUIRAZ_Tax | BI4: 200043946543000<!>20250326476411<!>CEAQU07_KEY@CEAQU07_GNODEB_MAIN_00D0772592030U_CE | BJ4: 1
A5: Huawei Gestao e Servicos de Telecomunicacoes do Brasil Ltda, | B5: 1766381519796641950 | C5: AZ0149 | D5: 319275 | E5: 6211 | F5: 1766381519796641866 | H5: 1766381519796641940 | I5: 1701733 | J5: 500001 | L5: fec633c658778a76202922c8ceed956501bfba414362284cb352c2f5fc6c5831 | M5: BM1 | O5: SERVICE_PROCUREMENT | P5: BM1_Financial | Q5: 10519123000197 | R5: 6211HG3360340-3062 | T5: 5 | U5: 2 | V5: SERVICE_PROCUREMENT | W5: 1 | X5: 1,0000000000 | Y5: 0 | Z5: 0 | AA5: 1 | AB5: BRL | AC5: 3000000246 | AD5: N | AK5: 38,528 | AL5: 7,02 INSTALACAO | AT5: Pay On Agreement | AU5: BRA | AV5: AC2 | AW5: 1 | AX5: RRU/AAU Dismantling (1-3 RRUs/AAUs) | AZ5: 【TT】▍AC1 (90,00%, INV AC -30D, Complete 90%) / AC2 (10,00%, INV AC -30D, Complete 100%) ▍ | BB5: 8812441757 | BC5: 56A0M7N | BE5: FPAMULTBRA25032510450326B1 | BF5: 00A07725232125 | BG5: SITE | BH5: BR_AL_MACEIO_Tax | BI5: 200045902309000<!>20250708589335<!>LOT_AL584624_00D07925490423_AL | BJ5: 1
A1115: Total | BH1115: =SUBTOTAL(103,Tabela_Base_Financeiro[PO Ship TO]) -> 2 | CM1115: =SUBTOTAL(103,Tabela_Base_Financeiro[TOTAL]) -> 0

Sheet COD. PROJETOS
B3: Project Code | C3: PROJETO | D3: OPERADORA
B4: 56A0939 | C4: VIVO WL | D4: VIVO
B5: 56A0A2P | C5: VIVO MW | D5: VIVO
B6: 56A0GFT | C6: VIVO WL | D6: VIVO
B7: 56A0F8R | C7: VIVO JERI | D7: VIVO
B8: 56A0HN1 | C8: VIVO MW | D8: VIVO
B9: 56A0CCC | C9: TIM WL | D9: TIM
B10: 56A05CP | C10: TIM MW | D10: TIM
B11: 56A08Y1 | C11: TIM BATTERY | D11: TIM
B12: 56A0CP2 | C12: CLARO WL | D12: CLARO
B13: 56A0G11 | C13: CLARO BATTERY | D13: CLARO
B14: 56A0KFU | C14: TIM WL | D14: TIM
... B26: 56A0T27 | C26: TIM SWAP | D26: TIM

Sheet BASE MUNICÍPIO
B2: Colunas1 | C2: Colunas2 | D2: Colunas3
B3: 18NLTICP01 | C3: TIJUCAS | D3: SC
B4: 3SLAUTC01 | C4: ARAUCARIA | D4: PR
B5: 4GBABDA5857 | C5: SALVADOR | D5: BA
B6: 4G-SAIG06 | C6: SALVADOR | D6: BA
B7: 7NLFSCE02 | C7: FEIRA DE SANTANA | D7: BA
B8: AAG | C8: ALAGOA GRANDE | D8: PB
B9: AAJ | C9: FORTALEZA | D9: CE
B10: AAL | C10: ARACOIABA | D10: CE
B11: AAX | C11: ARAPIRACA | D11: AL
B12: ABI | C12: ABAIARA | D12: CE
B13: ABM | C13: JABOATÃO DOS GUARARAPES | D13: PE
... B324: BASDR_0092 | C324: SALVADOR | D324: BA
B325: BASDR_0092_LIT | D325: BA
B326: BASER04 | C326: SERRINHA | D326: BA
B327: BASMF03 | C327: SIMÕES FILHO | D327: BA
B328: BASMF05 | C328: SIMÕES FILHO | D328: BA
B329: BASMF09 | C329: SIMÕES FILHO | D329: BA
B330: BASMF18 | C330: SIMÕES FILHO | D330: BA
B331: BASMF22 | C331: SIMÕES FILHO | D331: BA
B332: BASMF23 | C332: SIMÕES FILHO | D332: BA
B333: BASNB01 | C333: SANTA BÁRBARA | D333: BA
B334: BASNT01 | C334: SANTANA | D334: BA
B335: BASTZ03 | C335: ARACI | D335: BA
B336: BASUY01 | C336: SANTA LUZIA | D336: BA
B337: BATAP01 | C337: TAPIRAMUTÁ | D337: BA
... B464: CECUC04 | C464: CAUCAIA | D464: CE
B465: CECUC06 | D465: CE
B466: CECUC07 | C466: CAUCAIA | D466: CE
B467: CECUC11 | C467: CAUCAIA | D467: CE
B468: CECUC14 | C468: CAUCAIA | D468: CE
B469: CECVL02 | D469: CE
B470: CECZW01 | D470: CE
B471: CEEDS07 | C471: FORTALEZA | D471: CE
B472: CEEDS25 | C472: FORTALEZA | D472: CE
B473: CEESB03 | C473: EUSÉBIO | D473: CE
B474: CEFLA90 | C474: FORTALEZA | D474: CE
B475: CEHZT02 | C475: HORIZONTE | D475: CE
B476: CEIGE04 | C476: ITAPAGÉ | D476: CE
B477: CEIRA90 | D477: CE
B478: CEJNE07 | C478: JUAZEIRO DO NORTE | D478: CE
B479: CEL | C479: CEDRO | D479: CE
B480: CELVM01 | D480: CE
B481: CEMCW02 | C481: MARACANAU | D481: CE
B482: CEMCW03 | C482: MARACANAU | D482: CE
B483: CEMCW04 | D483: CE
B484: CEMES02 | C484: FORTALEZA | D484: CE
B485: CEMES07 | C485: FORTALEZA | D485: CE
B486: CEMES10 | C486: FORTALEZA | D486: CE
B487: CEMGS01 | D487: CE
B488: CEMRT01 | D488: CE
B489: CEPAC04 | C489: FORTALEZA | D489: CE
B490: CEPAC06 | C490: FORTALEZA | D490: CE
B491: CEPAC07 | C491: FORTALEZA | D491: CE
B492: CEPAC08 | C492: FORTALEZA | D492: CE
B493: CEPAC09 | C493: FORTALEZA | D493: CE
B494: CEPAC10 | C494: FORTALEZA | D494: CE
B495: CEPAC11 | C495: FORTALEZA | D495: CE
B496: CEPAR03 | C496: FORTALEZA | D496: CE
B497: CEPAR05 | C497: FORTALEZA | D497: CE
B498: CEPAR06 | C498: FORTALEZA | D498: CE
B499: CEPAR09 | C499: FORTALEZA | D499: CE
B500: CEPAR11 | C500: FORTALEZA | D500: CE
... B512: CEPJS01 | C512: PACAJUS | D512: CE
B513: CEPJS02 | D513: CE
B514: CEPJSR2 | C514: HORIZONTE | D514: CE
B515: CEPMC01 | C515: PALMÁCIA | D515: CE
B516: CER | C516: CAPOEIRAS | D516: PE
B517: CERUS01 | C517: RUSSAS | D517: CE
B518: CES | C518: FORTALEZA | D518: CE
B519: CESGA02 | C519: SÃO GONÇALO DO AMARANTE | D519: CE
B520: CESOL03 | D520: CE
B521: CET | C521: TERESINA | D521: PI
B522: CETRA02 | C522: TRAIRI | D522: CE
B523: CEVRZ01 | D523: CE
B524: CEVRZ02 | D524: CE
B525: CFC | C525: FORTALEZA | D525: CE
B526: CFO_RO | C526: CACOAL | D526: RO
B527: CFX | C527: CAMOCIM DE SÃO FÉLIX | D527: PE
B528: CGO | C528: CAPITÃO GERVÁSIO OLIVEIRA | D528: PI
B530: CHN | C530: BRASÍLIA | D530: DF
B531: CHR | C531: CACHOEIRINHA | D531: PE
B532: CIA | C532: CHÃ DE ALEGRIA | D532: PE
B533: CIS | C533: CANDEIAS | D533: BA
B534: CIV | C534: RECIFE | D534: PE
B535: CJI-VMM | C535: CAJARI - VITÓRIA DO MEARIM | D535: MA
B536: CJU | C536: FORTALEZA | D536: CE
B537: CLB | C537: MACEIÓ | D537: AL
... B590: CVZ | C590: CEDRO | D590: CE
B591: CWL
B592: CXA_GO | C592: CRIXÁS | D592: GO
B593: CXD | C593: CRIXÁS | D593: GO
B594: CXT | C594: RECIFE | D594: PE
B595: CYJ | C595: FORTALEZA | D595: CE
B596: CZH | C596: COCALZINHO DE GOIÁS | D596: GO
B597: DDC | C597: RECIFE | D597: PE
B598: DET | C598: GARANHUNS | D598: PE
B599: DFGMA08 | C599: BRASÍLIA | D599: DF
B600: DFSQN07 | C600: BRASÍLIA | D600: DF
B601: DFSQN09 | C601: BRASÍLIA | D601: DF
...

Sheet COD. FAT
A3: WL
A4: CODE | B4: TAX CODE
A6: 8812288263 | B6: 7.02
A7: 8812288264 | B7: 7.02
A8: 8812288265 | B8: 7.02
A9: 8812288266 | B9: 7.02
A10: 8812288267 | B10: 7.02
A11: 8812288268 | B11: 7.02
A12: 8812288269 | B12: 7.02
A13: 8812288270 | B13: 7.02
A14: 8812288271 | B14: 7.02
A15: 8812288272 | B15: 7.02
A17: 8812288273 | B17: 7.02
A18: 8812288274 | B18: 7.02
A19: 8812288275 | B19: 7.02
A20: 8812288276 | B20: 7.02
A21: 8812288277 | B21: 7.02
A22: 8812288278 | B22: 7.02
... A118: 8818188310 | B118: 7.02
A120: MW
A121: BOM CODE | B121: TAX CODE
A123: 8812288355 | B123: 7.02
A124: 8812288356 | B124: 7.02
A125: 8812288357 | B125: 7.02
A126: 8812288358 | B126: 7.02
A127: 8812288359 | B127: 7.02
A128: 8812288360 | B128: 7.02
A129: 8812288361 | B129: 7.02
A131: 8812288362 | B131: 7.02
A132: 8812288363 | B132: 7.02
A133: 8812288364 | B133: 7.02
A134: 8812288365 | B134: 7.02
A135: 8812288366 | B135: 7.02
... A184: 8812288401 | B184: 7.02
A186: CW
A187: CODE | B187: TAX CODE
A189: 8818188174 | B189: 7.02
A190: 8818188175 | B190: 7.02
A191: 8818188176 | B191: 7.02
A192: 8818188177 | B192: 7.02
A193: 8818188178 | B193: 7.02
A194: 8818188179 | B194: 7.02
A195: 8818188180 | B195: 7.02
A196: 8818188181 | B196: 7.02
A197: 8818188182 | B197: 7.02
A198: 8818188183 | B198: 7.02
A199: 8818188184 | B199: 7.02
A200: 8818188185 | B200: 7.02
... A316: 88940461 | B316: 7.02

Sheet MUNICIPIO
A2: SITE | B2: SITE2 | C2: PROJETO | D2: SITE_ID | E2: MUNICÍPIO | F2: UF | G2: ESCOPO | H2: CIDADE
A3: ='BASE FINANCEIRO'!#REF! -> #REF! | B3: =MID(A3,36,14) -> #REF! | C3: tim | D3: =IF(VLOOKUP('BASE FINANCEIRO'!#REF!,'COD. PROJETOS'!B:D,3,0)="VIVO",MID('BASE FINANCEIRO'!#REF!,36,3),IF(VLOOKUP('BASE FINANCEIRO'!#REF!,'COD. PROJETOS'!B:D,3,0),MID('BASE FINANCEIRO'!#REF!,36,7),IF(VLOOKUP('BASE FINANCEIRO'!#REF!,'COD. PROJETOS'!B:D,3,0),MID('BASE FINANCEIRO'!#REF!,36,9),"PROJETO?"))) -> #REF! | E3: =VLOOKUP(D3,'BASE MUNICÍPIO'!B1:C24719,2,0) -> #REF! | F3: =VLOOKUP(D3,'BASE MUNICÍPIO'!B1:D24719,3,0) -> #REF! | G3: =IF(Tabela4[[#This Row],[PROJETO]]="CLARO",LEFT(Tabela4[[#This Row],[SITE2]],2),IF(Tabela4[[#This Row],[PROJETO]]="VIVO",RIGHT(LEFT(Tabela4[[#This Row],[SITE2]],10),2),""))
A4: ='BASE FINANCEIRO'!BI4 -> 200043946543000<!>20250326476411<!>CEAQU07_KEY@CEAQU07_GNODEB_MAIN_00D0772592030U_CE | B4: =MID(A4,36,14) -> CEAQU07_KEY@CE | C4: VIVO | D4: =IF(VLOOKUP('BASE FINANCEIRO'!BC4,'COD. PROJETOS'!B:D,3,0)="VIVO",MID('BASE FINANCEIRO'!BI4,36,3),IF(VLOOKUP('BASE FINANCEIRO'!BC4,'COD. PROJETOS'!B:D,3,0),MID('BASE FINANCEIRO'!BI4,36,7),IF(VLOOKUP('BASE FINANCEIRO'!BC4,'COD. PROJETOS'!B:D,3,0),MID('BASE FINANCEIRO'!BI4,36,9),"PROJETO?"))) -> #VALUE! | E4: =VLOOKUP(D4,'BASE MUNICÍPIO'!B2:C24720,2,0) -> #VALUE! | F4: =VLOOKUP(D4,'BASE MUNICÍPIO'!B2:D24720,3,0) -> #VALUE! | G4: =IF(Tabela4[[#This Row],[PROJETO]]="CLARO",LEFT(Tabela4[[#This Row],[SITE2]],2),IF(Tabela4[[#This Row],[PROJETO]]="VIVO",RIGHT(LEFT(Tabela4[[#This Row],[SITE2]],10),2),"")) -> KE
A5: ='BASE FINANCEIRO'!BI46 -> 0 | B5: =MID(A5,36,14) | C5: VIVO | D5: =IF(VLOOKUP('BASE FINANCEIRO'!BC46,'COD. PROJETOS'!B:D,3,0)="VIVO",MID('BASE FINANCEIRO'!BI46,36,3),IF(VLOOKUP('BASE FINANCEIRO'!BC46,'COD. PROJETOS'!B:D,3,0),MID('BASE FINANCEIRO'!BI46,36,7),IF(VLOOKUP('BASE FINANCEIRO'!BC46,'COD. PROJETOS'!B:D,3,0),MID('BASE FINANCEIRO'!BI46,36,9),"PROJETO?"))) -> #N/A | E5: =VLOOKUP(D5,'BASE MUNICÍPIO'!B3:C24721,2,0) -> #N/A | F5: =VLOOKUP(D5,'BASE MUNICÍPIO'!B3:D24721,3,0) -> #N/A | G5: =IF(Tabela4[[#This Row],[PROJETO]]="CLARO",LEFT(Tabela4[[#This Row],[SITE2]],2),IF(Tabela4[[#This Row],[PROJETO]]="VIVO",RIGHT(LEFT(Tabela4[[#This Row],[SITE2]],10),2),""))
A6: ='BASE FINANCEIRO'!BI47 -> 0 | B6: =MID(A6,36,14) | C6: VIVO | D6: =IF(VLOOKUP('BASE FINANCEIRO'!BC47,'COD. PROJETOS'!B:D,3,0)="VIVO",MID('BASE FINANCEIRO'!BI47,36,3),IF(VLOOKUP('BASE FINANCEIRO'!BC47,'COD. PROJETOS'!B:D,3,0),MID('BASE FINANCEIRO'!BI47,36,7),IF(VLOOKUP('BASE FINANCEIRO'!BC47,'COD. PROJETOS'!B:D,3,0),MID('BASE FINANCEIRO'!BI47,36,9),"PROJETO?"))) -> #N/A | E6: =VLOOKUP(D6,'BASE MUNICÍPIO'!B3:C24722,2,0) -> #N/A | F6: =VLOOKUP(D6,'BASE MUNICÍPIO'!B3:D24722,3,0) -> #N/A | G6: =IF(Tabela4[[#This Row],[PROJETO]]="CLARO",LEFT(Tabela4[[#This Row],[SITE2]],2),IF(Tabela4[[#This Row],[PROJETO]]="VIVO",RIGHT(LEFT(Tabela4[[#This Row],[SITE2]],10),2),""))
A7: ='BASE FINANCEIRO'!BI48 -> 0 | B7: =MID(A7,36,14) | C7: VIVO | D7: =IF(VLOOKUP('BASE FINANCEIRO'!BC48,'COD. PROJETOS'!B:D,3,0)="VIVO",MID('BASE FINANCEIRO'!BI48,36,3),IF(VLOOKUP('BASE FINANCEIRO'!BC48,'COD. PROJETOS'!B:D,3,0),MID('BASE FINANCEIRO'!BI48,36,7),IF(VLOOKUP('BASE FINANCEIRO'!BC48,'COD. PROJETOS'!B:D,3,0),MID('BASE FINANCEIRO'!BI48,36,9),"PROJETO?"))) -> #N/A | E7: =VLOOKUP(D7,'BASE MUNICÍPIO'!B4:C24723,2,0) -> #N/A | F7: =VLOOKUP(D7,'BASE MUNICÍPIO'!B4:D24723,3,0) -> #N/A | G7: =IF(Tabela4[[#This Row],[PROJETO]]="CLARO",LEFT(Tabela4[[#This Row],[SITE2]],2),IF(Tabela4[[#This Row],[PROJETO]]="VIVO",RIGHT(LEFT(Tabela4[[#This Row],[SITE2]],10),2),""))
A8: ='BASE FINANCEIRO'!BI49 -> 0 | B8: =MID(A8,36,14) | C8: VIVO | D8: =IF(VLOOKUP('BASE FINANCEIRO'!BC49,'COD. PROJETOS'!B:D,3,0)="VIVO",MID('BASE FINANCEIRO'!BI49,36,3),IF(VLOOKUP('BASE FINANCEIRO'!BC49,'COD. PROJETOS'!B:D,3,0),MID('BASE FINANCEIRO'!BI49,36,7),IF(VLOOKUP('BASE FINANCEIRO'!BC49,'COD. PROJETOS'!B:D,3,0),MID('BASE FINANCEIRO'!BI49,36,9),"PROJETO?"))) -> #N/A | E8: =VLOOKUP(D8,'BASE MUNICÍPIO'!B5:C24724,2,0) -> #N/A | F8: =VLOOKUP(D8,'BASE MUNICÍPIO'!B5:D24724,3,0) -> #N/A | G8: =IF(Tabela4[[#This Row],[PROJETO]]="CLARO",LEFT(Tabela4[[#This Row],[SITE2]],2),IF(Tabela4[[#This Row],[PROJETO]]="VIVO",RIGHT(LEFT(Tabela4[[#This Row],[SITE2]],10),2),""))
A9: ='BASE FINANCEIRO'!BI50 -> 0 | B9: =MID(A9,36,14) | C9: CLARO | D9: =IF(VLOOKUP('BASE FINANCEIRO'!BC50,'COD. PROJETOS'!B:D,3,0)="VIVO",MID('BASE FINANCEIRO'!BI50,36,3),IF(VLOOKUP('BASE FINANCEIRO'!BC50,'COD. PROJETOS'!B:D,3,0),MID('BASE FINANCEIRO'!BI50,36,7),IF(VLOOKUP('BASE FINANCEIRO'!BC50,'COD. PROJETOS'!B:D,3,0),MID('BASE FINANCEIRO'!BI50,36,9),"PROJETO?"))) -> #N/A | E9: =VLOOKUP(D9,'BASE MUNICÍPIO'!B6:C24725,2,0) -> #N/A | F9: =VLOOKUP(D9,'BASE MUNICÍPIO'!B6:D24725,3,0) -> #N/A | G9: =IF(Tabela4[[#This Row],[PROJETO]]="CLARO",LEFT(Tabela4[[#This Row],[SITE2]],2),IF(Tabela4[[#This Row],[PROJETO]]="VIVO",RIGHT(LEFT(Tabela4[[#This Row],[SITE2]],10),2),""))
A10: ='BASE FINANCEIRO'!BI51 -> 0 | B10: =MID(A10,36,14) | C10: VIVO | D10: =IF(VLOOKUP('BASE FINANCEIRO'!BC51,'COD. PROJETOS'!B:D,3,0)="VIVO",MID('BASE FINANCEIRO'!BI51,36,3),IF(VLOOKUP('BASE FINANCEIRO'!BC51,'COD. PROJETOS'!B:D,3,0),MID('BASE FINANCEIRO'!BI51,36,7),IF(VLOOKUP('BASE FINANCEIRO'!BC51,'COD. PROJETOS'!B:D,3,0),MID('BASE FINANCEIRO'!BI51,36,9),"PROJETO?"))) -> #N/A | E10: =VLOOKUP(D10,'BASE MUNICÍPIO'!B7:C24726,2,0) -> #N/A | F10: =VLOOKUP(D10,'BASE MUNICÍPIO'!B7:D24726,3,0) -> #N/A | G10: =IF(Tabela4[[#This Row],[PROJETO]]="CLARO",LEFT(Tabela4[[#This Row],[SITE2]],2),IF(Tabela4[[#This Row],[PROJETO]]="VIVO",RIGHT(LEFT(Tabela4[[#This Row],[SITE2]],10),2),""))
A11: ='BASE FINANCEIRO'!BI52 -> 0 | B11: =MID(A11,36,14) | C11: VIVO | D11: =IF(VLOOKUP('BASE FINANCEIRO'!BC52,'COD. PROJETOS'!B:D,3,0)="VIVO",MID('BASE FINANCEIRO'!BI52,36,3),IF(VLOOKUP('BASE FINANCEIRO'!BC52,'COD. PROJETOS'!B:D,3,0),MID('BASE FINANCEIRO'!BI52,36,7),IF(VLOOKUP('BASE FINANCEIRO'!BC52,'COD. PROJETOS'!B:D,3,0),MID('BASE FINANCEIRO'!BI52,36,9),"PROJETO?"))) -> #N/A | E11: =VLOOKUP(D11,'BASE MUNICÍPIO'!B8:C24727,2,0) -> #N/A | F11: =VLOOKUP(D11,'BASE MUNICÍPIO'!B8:D24727,3,0) -> #N/A | G11: =IF(Tabela4[[#This Row],[PROJETO]]="CLARO",LEFT(Tabela4[[#This Row],[SITE2]],2),IF(Tabela4[[#This Row],[PROJETO]]="VIVO",RIGHT(LEFT(Tabela4[[#This Row],[SITE2]],10),2),""))
A12: ='BASE FINANCEIRO'!BI53 -> 0 | B12: =MID(A12,36,14) | C12: VIVO | D12: =IF(VLOOKUP('BASE FINANCEIRO'!BC53,'COD. PROJETOS'!B:D,3,0)="VIVO",MID('BASE FINANCEIRO'!BI53,36,3),IF(VLOOKUP('BASE FINANCEIRO'!BC53,'COD. PROJETOS'!B:D,3,0),MID('BASE FINANCEIRO'!BI53,36,7),IF(VLOOKUP('BASE FINANCEIRO'!BC53,'COD. PROJETOS'!B:D,3,0),MID('BASE FINANCEIRO'!BI53,36,9),"PROJETO?"))) -> #N/A | E12: =VLOOKUP(D12,'BASE MUNICÍPIO'!B9:C24728,2,0) -> #N/A | F12: =VLOOKUP(D12,'BASE MUNICÍPIO'!B9:D24728,3,0) -> #N/A | G12: =IF(Tabela4[[#This Row],[PROJETO]]="CLARO",LEFT(Tabela4[[#This Row],[SITE2]],2),IF(Tabela4[[#This Row],[PROJETO]]="VIVO",RIGHT(LEFT(Tabela4[[#This Row],[SITE2]],10),2),""))
A13: ='BASE FINANCEIRO'!BI54 -> 0 | B13: =MID(A13,36,14) | C13: VIVO | D13: =IF(VLOOKUP('BASE FINANCEIRO'!BC54,'COD. PROJETOS'!B:D,3,0)="VIVO",MID('BASE FINANCEIRO'!BI54,36,3),IF(VLOOKUP('BASE FINANCEIRO'!BC54,'COD. PROJETOS'!B:D,3,0),MID('BASE FINANCEIRO'!BI54,36,7),IF(VLOOKUP('BASE FINANCEIRO'!BC54,'COD. PROJETOS'!B:D,3,0),MID('BASE FINANCEIRO'!BI54,36,9),"PROJETO?"))) -> #N/A | E13: =VLOOKUP(D13,'BASE MUNICÍPIO'!B10:C24729,2,0) -> #N/A | F13: =VLOOKUP(D13,'BASE MUNICÍPIO'!B10:D24729,3,0) -> #N/A | G13: =IF(Tabela4[[#This Row],[PROJETO]]="CLARO",LEFT(Tabela4[[#This Row],[SITE2]],2),IF(Tabela4[[#This Row],[PROJETO]]="VIVO",RIGHT(LEFT(Tabela4[[#This Row],[SITE2]],10),2),""))
A14: ='BASE FINANCEIRO'!BI55 -> 0 | B14: =MID(A14,36,14) | C14: VIVO | D14: =IF(VLOOKUP('BASE FINANCEIRO'!BC55,'COD. PROJETOS'!B:D,3,0)="VIVO",MID('BASE FINANCEIRO'!BI55,36,3),IF(VLOOKUP('BASE FINANCEIRO'!BC55,'COD. PROJETOS'!B:D,3,0),MID('BASE FINANCEIRO'!BI55,36,7),IF(VLOOKUP('BASE FINANCEIRO'!BC55,'COD. PROJETOS'!B:D,3,0),MID('BASE FINANCEIRO'!BI55,36,9),"PROJETO?"))) -> #N/A | E14: =VLOOKUP(D14,'BASE MUNICÍPIO'!B11:C24730,2,0) -> #N/A | F14: =VLOOKUP(D14,'BASE MUNICÍPIO'!B11:D24730,3,0) -> #N/A | G14: =IF(Tabela4[[#This Row],[PROJETO]]="CLARO",LEFT(Tabela4[[#This Row],[SITE2]],2),IF(Tabela4[[#This Row],[PROJETO]]="VIVO",RIGHT(LEFT(Tabela4[[#This Row],[SITE2]],10),2),""))
A15: ='BASE FINANCEIRO'!BI56 -> 0 | B15: =MID(A15,36,14) | C15: VIVO | D15: =IF(VLOOKUP('BASE FINANCEIRO'!BC56,'COD. PROJETOS'!B:D,3,0)="VIVO",MID('BASE FINANCEIRO'!BI56,36,3),IF(VLOOKUP('BASE FINANCEIRO'!BC56,'COD. PROJETOS'!B:D,3,0),MID('BASE FINANCEIRO'!BI56,36,7),IF(VLOOKUP('BASE FINANCEIRO'!BC56,'COD. PROJETOS'!B:D,3,0),MID('BASE FINANCEIRO'!BI56,36,9),"PROJETO?"))) -> #N/A | E15: =VLOOKUP(D15,'BASE MUNICÍPIO'!B12:C24731,2,0) -> #N/A | F15: =VLOOKUP(D15,'BASE MUNICÍPIO'!B12:D24731,3,0) -> #N/A | G15: =IF(Tabela4[[#This Row],[PROJETO]]="CLARO",LEFT(Tabela4[[#This Row],[SITE2]],2),IF(Tabela4[[#This Row],[PROJETO]]="VIVO",RIGHT(LEFT(Tabela4[[#This Row],[SITE2]],10),2),""))
A16: ='BASE FINANCEIRO'!BI57 -> 0 | B16: =MID(A16,36,14) | C16: VIVO | D16: =IF(VLOOKUP('BASE FINANCEIRO'!BC57,'COD. PROJETOS'!B:D,3,0)="VIVO",MID('BASE FINANCEIRO'!BI57,36,3),IF(VLOOKUP('BASE FINANCEIRO'!BC57,'COD. PROJETOS'!B:D,3,0),MID('BASE FINANCEIRO'!BI57,36,7),IF(VLOOKUP('BASE FINANCEIRO'!BC57,'COD. PROJETOS'!B:D,3,0),MID('BASE FINANCEIRO'!BI57,36,9),"PROJETO?"))) -> #N/A | E16: =VLOOKUP(D16,'BASE MUNICÍPIO'!B13:C24732,2,0) -> #N/A | F16: =VLOOKUP(D16,'BASE MUNICÍPIO'!B13:D24732,3,0) -> #N/A | G16: =IF(Tabela4[[#This Row],[PROJETO]]="CLARO",LEFT(Tabela4[[#This Row],[SITE2]],2),IF(Tabela4[[#This Row],[PROJETO]]="VIVO",RIGHT(LEFT(Tabela4[[#This Row],[SITE2]],10),2),""))
A17: ='BASE FINANCEIRO'!BI58 -> 0 | B17: =MID(A17,36,14) | C17: VIVO | D17: =IF(VLOOKUP('BASE FINANCEIRO'!BC58,'COD. PROJETOS'!B:D,3,0)="VIVO",MID('BASE FINANCEIRO'!BI58,36,3),IF(VLOOKUP('BASE FINANCEIRO'!BC58,'COD. PROJETOS'!B:D,3,0),MID('BASE FINANCEIRO'!BI58,36,7),IF(VLOOKUP('BASE FINANCEIRO'!BC58,'COD. PROJETOS'!B:D,3,0),MID('BASE FINANCEIRO'!BI58,36,9),"PROJETO?"))) -> #N/A | E17: =VLOOKUP(D17,'BASE MUNICÍPIO'!B14:C24733,2,0) -> #N/A | F17: =VLOOKUP(D17,'BASE MUNICÍPIO'!B14:D24733,3,0) -> #N/A | G17: =IF(Tabela4[[#This Row],[PROJETO]]="CLARO",LEFT(Tabela4[[#This Row],[SITE2]],2),IF(Tabela4[[#This Row],[PROJETO]]="VIVO",RIGHT(LEFT(Tabela4[[#This Row],[SITE2]],10),2),""))
A18: ='BASE FINANCEIRO'!#REF! -> #REF! | B18: =MID(A18,36,14) -> #REF! | C18: VIVO | D18: =IF(VLOOKUP('BASE FINANCEIRO'!#REF!,'COD. PROJETOS'!B:D,3,0)="VIVO",MID('BASE FINANCEIRO'!#REF!,36,3),IF(VLOOKUP('BASE FINANCEIRO'!#REF!,'COD. PROJETOS'!B:D,3,0),MID('BASE FINANCEIRO'!#REF!,36,7),IF(VLOOKUP('BASE FINANCEIRO'!#REF!,'COD. PROJETOS'!B:D,3,0),MID('BASE FINANCEIRO'!#REF!,36,9),"PROJETO?"))) -> #REF! | E18: =VLOOKUP(D18,'BASE MUNICÍPIO'!B15:C24734,2,0) -> #REF! | F18: =VLOOKUP(D18,'BASE MUNICÍPIO'!B15:D24734,3,0) -> #REF! | G18: =IF(Tabela4[[#This Row],[PROJETO]]="CLARO",LEFT(Tabela4[[#This Row],[SITE2]],2),IF(Tabela4[[#This Row],[PROJETO]]="VIVO",RIGHT(LEFT(Tabela4[[#This Row],[SITE2]],10),2),"")) -> #REF!
A19: ='BASE FINANCEIRO'!BI59 -> 0 | B19: =MID(A19,36,14) | C19: VIVO | D19: =IF(VLOOKUP('BASE FINANCEIRO'!BC59,'COD. PROJETOS'!B:D,3,0)="VIVO",MID('BASE FINANCEIRO'!BI59,36,3),IF(VLOOKUP('BASE FINANCEIRO'!BC59,'COD. PROJETOS'!B:D,3,0),MID('BASE FINANCEIRO'!BI59,36,7),IF(VLOOKUP('BASE FINANCEIRO'!BC59,'COD. PROJETOS'!B:D,3,0),MID('BASE FINANCEIRO'!BI59,36,9),"PROJETO?"))) -> #N/A | E19: =VLOOKUP(D19,'BASE MUNICÍPIO'!B16:C24735,2,0) -> #N/A | F19: =VLOOKUP(D19,'BASE MUNICÍPIO'!B16:D24735,3,0) -> #N/A | G19: =IF(Tabela4[[#This Row],[PROJETO]]="CLARO",LEFT(Tabela4[[#This Row],[SITE2]],2),IF(Tabela4[[#This Row],[PROJETO]]="VIVO",RIGHT(LEFT(Tabela4[[#This Row],[SITE2]],10),2),""))
A20: ='BASE FINANCEIRO'!BI60 -> 0 | B20: =MID(A20,36,14) | C20: VIVO | D20: =IF(VLOOKUP('BASE FINANCEIRO'!BC60,'COD. PROJETOS'!B:D,3,0)="VIVO",MID('BASE FINANCEIRO'!BI60,36,3),IF(VLOOKUP('BASE FINANCEIRO'!BC60,'COD. PROJETOS'!B:D,3,0),MID('BASE FINANCEIRO'!BI60,36,7),IF(VLOOKUP('BASE FINANCEIRO'!BC60,'COD. PROJETOS'!B:D,3,0),MID('BASE FINANCEIRO'!BI60,36,9),"PROJETO?"))) -> #N/A | E20: =VLOOKUP(D20,'BASE MUNICÍPIO'!B17:C24736,2,0) -> #N/A | F20: =VLOOKUP(D20,'BASE MUNICÍPIO'!B17:D24736,3,0) -> #N/A | G20: =IF(Tabela4[[#This Row],[PROJETO]]="CLARO",LEFT(Tabela4[[#This Row],[SITE2]],2),IF(Tabela4[[#This Row],[PROJETO]]="VIVO",RIGHT(LEFT(Tabela4[[#This Row],[SITE2]],10),2),""))
A21: ='BASE FINANCEIRO'!BI61 -> 0 | B21: =MID(A21,36,14) | C21: VIVO | D21: =IF(VLOOKUP('BASE FINANCEIRO'!BC61,'COD. PROJETOS'!B:D,3,0)="VIVO",MID('BASE FINANCEIRO'!BI61,36,3),IF(VLOOKUP('BASE FINANCEIRO'!BC61,'COD. PROJETOS'!B:D,3,0),MID('BASE FINANCEIRO'!BI61,36,7),IF(VLOOKUP('BASE FINANCEIRO'!BC61,'COD. PROJETOS'!B:D,3,0),MID('BASE FINANCEIRO'!BI61,36,9),"PROJETO?"))) -> #N/A | E21: =VLOOKUP(D21,'BASE MUNICÍPIO'!B18:C24737,2,0) -> #N/A | F21: =VLOOKUP(D21,'BASE MUNICÍPIO'!B18:D24737,3,0) -> #N/A | G21: =IF(Tabela4[[#This Row],[PROJETO]]="CLARO",LEFT(Tabela4[[#This Row],[SITE2]],2),IF(Tabela4[[#This Row],[PROJETO]]="VIVO",RIGHT(LEFT(Tabela4[[#This Row],[SITE2]],10),2),""))
A22: ='BASE FINANCEIRO'!BI62 -> 0 | B22: =MID(A22,36,14) | C22: VIVO | D22: =IF(VLOOKUP('BASE FINANCEIRO'!BC62,'COD. PROJETOS'!B:D,3,0)="VIVO",MID('BASE FINANCEIRO'!BI62,36,3),IF(VLOOKUP('BASE FINANCEIRO'!BC62,'COD. PROJETOS'!B:D,3,0),MID('BASE FINANCEIRO'!BI62,36,7),IF(VLOOKUP('BASE FINANCEIRO'!BC62,'COD. PROJETOS'!B:D,3,0),MID('BASE FINANCEIRO'!BI62,36,9),"PROJETO?"))) -> #N/A | E22: =VLOOKUP(D22,'BASE MUNICÍPIO'!B19:C24738,2,0) -> #N/A | F22: =VLOOKUP(D22,'BASE MUNICÍPIO'!B19:D24738,3,0) -> #N/A | G22: =IF(Tabela4[[#This Row],[PROJETO]]="CLARO",LEFT(Tabela4[[#This Row],[SITE2]],2),IF(Tabela4[[#This Row],[PROJETO]]="VIVO",RIGHT(LEFT(Tabela4[[#This Row],[SITE2]],10),2),""))
A23: ='BASE FINANCEIRO'!BI63 -> 0 | B23: =MID(A23,36,14) | C23: VIVO | D23: =IF(VLOOKUP('BASE FINANCEIRO'!BC63,'COD. PROJETOS'!B:D,3,0)="VIVO",MID('BASE FINANCEIRO'!BI63,36,3),IF(VLOOKUP('BASE FINANCEIRO'!BC63,'COD. PROJETOS'!B:D,3,0),MID('BASE FINANCEIRO'!BI63,36,7),IF(VLOOKUP('BASE FINANCEIRO'!BC63,'COD. PROJETOS'!B:D,3,0),MID('BASE FINANCEIRO'!BI63,36,9),"PROJETO?"))) -> #N/A | E23: =VLOOKUP(D23,'BASE MUNICÍPIO'!B20:C24739,2,0) -> #N/A | F23: =VLOOKUP(D23,'BASE MUNICÍPIO'!B20:D24739,3,0) -> #N/A | G23: =IF(Tabela4[[#This Row],[PROJETO]]="CLARO",LEFT(Tabela4[[#This Row],[SITE2]],2),IF(Tabela4[[#This Row],[PROJETO]]="VIVO",RIGHT(LEFT(Tabela4[[#This Row],[SITE2]],10),2),""))
A24: ='BASE FINANCEIRO'!BI64 -> 0 | B24: =MID(A24,36,14) | C24: VIVO | D24: =IF(VLOOKUP('BASE FINANCEIRO'!BC64,'COD. PROJETOS'!B:D,3,0)="VIVO",MID('BASE FINANCEIRO'!BI64,36,3),IF(VLOOKUP('BASE FINANCEIRO'!BC64,'COD. PROJETOS'!B:D,3,0),MID('BASE FINANCEIRO'!BI64,36,7),IF(VLOOKUP('BASE FINANCEIRO'!BC64,'COD. PROJETOS'!B:D,3,0),MID('BASE FINANCEIRO'!BI64,36,9),"PROJETO?"))) -> #N/A | E24: =VLOOKUP(D24,'BASE MUNICÍPIO'!B21:C24740,2,0) -> #N/A | F24: =VLOOKUP(D24,'BASE MUNICÍPIO'!B21:D24740,3,0) -> #N/A | G24: =IF(Tabela4[[#This Row],[PROJETO]]="CLARO",LEFT(Tabela4[[#This Row],[SITE2]],2),IF(Tabela4[[#This Row],[PROJETO]]="VIVO",RIGHT(LEFT(Tabela4[[#This Row],[SITE2]],10),2),""))
A25: ='BASE FINANCEIRO'!BI65 -> 0 | B25: =MID(A25,36,14) | C25: VIVO | D25: =IF(VLOOKUP('BASE FINANCEIRO'!BC65,'COD. PROJETOS'!B:D,3,0)="VIVO",MID('BASE FINANCEIRO'!BI65,36,3),IF(VLOOKUP('BASE FINANCEIRO'!BC65,'COD. PROJETOS'!B:D,3,0),MID('BASE FINANCEIRO'!BI65,36,7),IF(VLOOKUP('BASE FINANCEIRO'!BC65,'COD. PROJETOS'!B:D,3,0),MID('BASE FINANCEIRO'!BI65,36,9),"PROJETO?"))) -> #N/A | E25: =VLOOKUP(D25,'BASE MUNICÍPIO'!B22:C24741,2,0) -> #N/A | F25: =VLOOKUP(D25,'BASE MUNICÍPIO'!B22:D24741,3,0) -> #N/A | G25: =IF(Tabela4[[#This Row],[PROJETO]]="CLARO",LEFT(Tabela4[[#This Row],[SITE2]],2),IF(Tabela4[[#This Row],[PROJETO]]="VIVO",RIGHT(LEFT(Tabela4[[#This Row],[SITE2]],10),2),""))
A26: ='BASE FINANCEIRO'!BI66 -> 0 | B26: =MID(A26,36,14) | C26: VIVO | D26: =IF(VLOOKUP('BASE FINANCEIRO'!BC66,'COD. PROJETOS'!B:D,3,0)="VIVO",MID('BASE FINANCEIRO'!BI66,36,3),IF(VLOOKUP('BASE FINANCEIRO'!BC66,'COD. PROJETOS'!B:D,3,0),MID('BASE FINANCEIRO'!BI66,36,7),IF(VLOOKUP('BASE FINANCEIRO'!BC66,'COD. PROJETOS'!B:D,3,0),MID('BASE FINANCEIRO'!BI66,36,9),"PROJETO?"))) -> #N/A | E26: =VLOOKUP(D26,'BASE MUNICÍPIO'!B23:C24742,2,0) -> #N/A | F26: =VLOOKUP(D26,'BASE MUNICÍPIO'!B23:D24742,3,0) -> #N/A | G26: =IF(Tabela4[[#This Row],[PROJETO]]="CLARO",LEFT(Tabela4[[#This Row],[SITE2]],2),IF(Tabela4[[#This Row],[PROJETO]]="VIVO",RIGHT(LEFT(Tabela4[[#This Row],[SITE2]],10),2),""))
A27: ='BASE FINANCEIRO'!BI67 -> 0 | B27: =MID(A27,36,14) | C27: VIVO | D27: =IF(VLOOKUP('BASE FINANCEIRO'!BC67,'COD. PROJETOS'!B:D,3,0)="VIVO",MID('BASE FINANCEIRO'!BI67,36,3),IF(VLOOKUP('BASE FINANCEIRO'!BC67,'COD. PROJETOS'!B:D,3,0),MID('BASE FINANCEIRO'!BI67,36,7),IF(VLOOKUP('BASE FINANCEIRO'!BC67,'COD. PROJETOS'!B:D,3,0),MID('BASE FINANCEIRO'!BI67,36,9),"PROJETO?"))) -> #N/A | E27: =VLOOKUP(D27,'BASE MUNICÍPIO'!B23:C24743,2,0) -> #N/A | F27: =VLOOKUP(D27,'BASE MUNICÍPIO'!B23:D24743,3,0) -> #N/A | G27: =IF(Tabela4[[#This Row],[PROJETO]]="CLARO",LEFT(Tabela4[[#This Row],[SITE2]],2),IF(Tabela4[[#This Row],[PROJETO]]="VIVO",RIGHT(LEFT(Tabela4[[#This Row],[SITE2]],10),2),""))
A28: ='BASE FINANCEIRO'!BI68 -> 0 | B28: =MID(A28,36,14) | C28: VIVO | D28: =IF(VLOOKUP('BASE FINANCEIRO'!BC68,'COD. PROJETOS'!B:D,3,0)="VIVO",MID('BASE FINANCEIRO'!BI68,36,3),IF(VLOOKUP('BASE FINANCEIRO'!BC68,'COD. PROJETOS'!B:D,3,0),MID('BASE FINANCEIRO'!BI68,36,7),IF(VLOOKUP('BASE FINANCEIRO'!BC68,'COD. PROJETOS'!B:D,3,0),MID('BASE FINANCEIRO'!BI68,36,9),"PROJETO?"))) -> #N/A | E28: =VLOOKUP(D28,'BASE MUNICÍPIO'!B23:C24744,2,0) -> #N/A | F28: =VLOOKUP(D28,'BASE MUNICÍPIO'!B23:D24744,3,0) -> #N/A | G28: =IF(Tabela4[[#This Row],[PROJETO]]="CLARO",LEFT(Tabela4[[#This Row],[SITE2]],2),IF(Tabela4[[#This Row],[PROJETO]]="VIVO",RIGHT(LEFT(Tabela4[[#This Row],[SITE2]],10),2),""))
A29: ='BASE FINANCEIRO'!BI69 -> 0 | B29: =MID(A29,36,14) | C29: VIVO | D29: =IF(VLOOKUP('BASE FINANCEIRO'!BC69,'COD. PROJETOS'!B:D,3,0)="VIVO",MID('BASE FINANCEIRO'!BI69,36,3),IF(VLOOKUP('BASE FINANCEIRO'!BC69,'COD. PROJETOS'!B:D,3,0),MID('BASE FINANCEIRO'!BI69,36,7),IF(VLOOKUP('BASE FINANCEIRO'!BC69,'COD. PROJETOS'!B:D,3,0),MID('BASE FINANCEIRO'!BI69,36,9),"PROJETO?"))) -> #N/A | E29: =VLOOKUP(D29,'BASE MUNICÍPIO'!B24:C24745,2,0) -> #N/A | F29: =VLOOKUP(D29,'BASE MUNICÍPIO'!B24:D24745,3,0) -> #N/A | G29: =IF(Tabela4[[#This Row],[PROJETO]]="CLARO",LEFT(Tabela4[[#This Row],[SITE2]],2),IF(Tabela4[[#This Row],[PROJETO]]="VIVO",RIGHT(LEFT(Tabela4[[#This Row],[SITE2]],10),2),""))
A30: ='BASE FINANCEIRO'!BI70 -> 0 | B30: =MID(A30,36,14) | C30: VIVO | D30: =IF(VLOOKUP('BASE FINANCEIRO'!BC70,'COD. PROJETOS'!B:D,3,0)="VIVO",MID('BASE FINANCEIRO'!BI70,36,3),IF(VLOOKUP('BASE FINANCEIRO'!BC70,'COD. PROJETOS'!B:D,3,0),MID('BASE FINANCEIRO'!BI70,36,7),IF(VLOOKUP('BASE FINANCEIRO'!BC70,'COD. PROJETOS'!B:D,3,0),MID('BASE FINANCEIRO'!BI70,36,9),"PROJETO?"))) -> #N/A | E30: =VLOOKUP(D30,'BASE MUNICÍPIO'!B24:C24746,2,0) -> #N/A | F30: =VLOOKUP(D30,'BASE MUNICÍPIO'!B24:D24746,3,0) -> #N/A | G30: =IF(Tabela4[[#This Row],[PROJETO]]="CLARO",LEFT(Tabela4[[#This Row],[SITE2]],2),IF(Tabela4[[#This Row],[PROJETO]]="VIVO",RIGHT(LEFT(Tabela4[[#This Row],[SITE2]],10),2),""))
A31: ='BASE FINANCEIRO'!#REF! -> #REF! | B31: =MID(A31,36,14) -> #REF! | C31: VIVO | D31: =IF(VLOOKUP('BASE FINANCEIRO'!#REF!,'COD. PROJETOS'!B:D,3,0)="VIVO",MID('BASE FINANCEIRO'!#REF!,36,3),IF(VLOOKUP('BASE FINANCEIRO'!#REF!,'COD. PROJETOS'!B:D,3,0),MID('BASE FINANCEIRO'!#REF!,36,7),IF(VLOOKUP('BASE FINANCEIRO'!#REF!,'COD. PROJETOS'!B:D,3,0),MID('BASE FINANCEIRO'!#REF!,36,9),"PROJETO?"))) -> #REF! | E31: =VLOOKUP(D31,'BASE MUNICÍPIO'!B25:C24747,2,0) -> #REF! | F31: =VLOOKUP(D31,'BASE MUNICÍPIO'!B25:D24747,3,0) -> #REF! | G31: =IF(Tabela4[[#This Row],[PROJETO]]="CLARO",LEFT(Tabela4[[#This Row],[SITE2]],2),IF(Tabela4[[#This Row],[PROJETO]]="VIVO",RIGHT(LEFT(Tabela4[[#This Row],[SITE2]],10),2),"")) -> #REF!
A32: ='BASE FINANCEIRO'!BI71 -> 0 | B32: =MID(A32,36,14) | C32: VIVO | D32: =IF(VLOOKUP('BASE FINANCEIRO'!BC71,'COD. PROJETOS'!B:D,3,0)="VIVO",MID('BASE FINANCEIRO'!BI71,36,3),IF(VLOOKUP('BASE FINANCEIRO'!BC71,'COD. PROJETOS'!B:D,3,0),MID('BASE FINANCEIRO'!BI71,36,7),IF(VLOOKUP('BASE FINANCEIRO'!BC71,'COD. PROJETOS'!B:D,3,0),MID('BASE FINANCEIRO'!BI71,36,9),"PROJETO?"))) -> #N/A | E32: =VLOOKUP(D32,'BASE MUNICÍPIO'!B26:C24748,2,0) -> #N/A | F32: =VLOOKUP(D32,'BASE MUNICÍPIO'!B26:D24748,3,0) -> #N/A | G32: =IF(Tabela4[[#This Row],[PROJETO]]="CLARO",LEFT(Tabela4[[#This Row],[SITE2]],2),IF(Tabela4[[#This Row],[PROJETO]]="VIVO",RIGHT(LEFT(Tabela4[[#This Row],[SITE2]],10),2),""))
A33: ='BASE FINANCEIRO'!BI72 -> 0 | B33: =MID(A33,36,14) | C33: VIVO | D33: =IF(VLOOKUP('BASE FINANCEIRO'!BC72,'COD. PROJETOS'!B:D,3,0)="VIVO",MID('BASE FINANCEIRO'!BI72,36,3),IF(VLOOKUP('BASE FINANCEIRO'!BC72,'COD. PROJETOS'!B:D,3,0),MID('BASE FINANCEIRO'!BI72,36,7),IF(VLOOKUP('BASE FINANCEIRO'!BC72,'COD. PROJETOS'!B:D,3,0),MID('BASE FINANCEIRO'!BI72,36,9),"PROJETO?"))) -> #N/A | E33: =VLOOKUP(D33,'BASE MUNICÍPIO'!B27:C24749,2,0) -> #N/A | F33: =VLOOKUP(D33,'BASE MUNICÍPIO'!B27:D24749,3,0) -> #N/A | G33: =IF(Tabela4[[#This Row],[PROJETO]]="CLARO",LEFT(Tabela4[[#This Row],[SITE2]],2),IF(Tabela4[[#This Row],[PROJETO]]="VIVO",RIGHT(LEFT(Tabela4[[#This Row],[SITE2]],10),2),""))
A34: ='BASE FINANCEIRO'!BI73 -> 0 | B34: =MID(A34,36,14) | C34: VIVO | D34: =IF(VLOOKUP('BASE FINANCEIRO'!BC73,'COD. PROJETOS'!B:D,3,0)="VIVO",MID('BASE FINANCEIRO'!BI73,36,3),IF(VLOOKUP('BASE FINANCEIRO'!BC73,'COD. PROJETOS'!B:D,3,0),MID('BASE FINANCEIRO'!BI73,36,7),IF(VLOOKUP('BASE FINANCEIRO'!BC73,'COD. PROJETOS'!B:D,3,0),MID('BASE FINANCEIRO'!BI73,36,9),"PROJETO?"))) -> #N/A | E34: =VLOOKUP(D34,'BASE MUNICÍPIO'!B28:C24750,2,0) -> #N/A | F34: =VLOOKUP(D34,'BASE MUNICÍPIO'!B28:D24750,3,0) -> #N/A | G34: =IF(Tabela4[[#This Row],[PROJETO]]="CLARO",LEFT(Tabela4[[#This Row],[SITE2]],2),IF(Tabela4[[#This Row],[PROJETO]]="VIVO",RIGHT(LEFT(Tabela4[[#This Row],[SITE2]],10),2),""))
A35: ='BASE FINANCEIRO'!BI74 -> 0 | B35: =MID(A35,36,14) | C35: VIVO | D35: =IF(VLOOKUP('BASE FINANCEIRO'!BC74,'COD. PROJETOS'!B:D,3,0)="VIVO",MID('BASE FINANCEIRO'!BI74,36,3),IF(VLOOKUP('BASE FINANCEIRO'!BC74,'COD. PROJETOS'!B:D,3,0),MID('BASE FINANCEIRO'!BI74,36,7),IF(VLOOKUP('BASE FINANCEIRO'!BC74,'COD. PROJETOS'!B:D,3,0),MID('BASE FINANCEIRO'!BI74,36,9),"PROJETO?"))) -> #N/A | E35: =VLOOKUP(D35,'BASE MUNICÍPIO'!B28:C24751,2,0) -> #N/A | F35: =VLOOKUP(D35,'BASE MUNICÍPIO'!B28:D24751,3,0) -> #N/A | G35: =IF(Tabela4[[#This Row],[PROJETO]]="CLARO",LEFT(Tabela4[[#This Row],[SITE2]],2),IF(Tabela4[[#This Row],[PROJETO]]="VIVO",RIGHT(LEFT(Tabela4[[#This Row],[SITE2]],10),2),""))
A36: ='BASE FINANCEIRO'!BI75 -> 0 | B36: =MID(A36,36,14) | C36: VIVO | D36: =IF(VLOOKUP('BASE FINANCEIRO'!BC75,'COD. PROJETOS'!B:D,3,0)="VIVO",MID('BASE FINANCEIRO'!BI75,36,3),IF(VLOOKUP('BASE FINANCEIRO'!BC75,'COD. PROJETOS'!B:D,3,0),MID('BASE FINANCEIRO'!BI75,36,7),IF(VLOOKUP('BASE FINANCEIRO'!BC75,'COD. PROJETOS'!B:D,3,0),MID('BASE FINANCEIRO'!BI75,36,9),"PROJETO?"))) -> #N/A | E36: =VLOOKUP(D36,'BASE MUNICÍPIO'!B29:C24752,2,0) -> #N/A | F36: =VLOOKUP(D36,'BASE MUNICÍPIO'!B29:D24752,3,0) -> #N/A | G36: =IF(Tabela4[[#This Row],[PROJETO]]="CLARO",LEFT(Tabela4[[#This Row],[SITE2]],2),IF(Tabela4[[#This Row],[PROJETO]]="VIVO",RIGHT(LEFT(Tabela4[[#This Row],[SITE2]],10),2),""))
A37: ='BASE FINANCEIRO'!BI76 -> 0 | B37: =MID(A37,36,14) | C37: VIVO | D37: =IF(VLOOKUP('BASE FINANCEIRO'!BC76,'COD. PROJETOS'!B:D,3,0)="VIVO",MID('BASE FINANCEIRO'!BI76,36,3),IF(VLOOKUP('BASE FINANCEIRO'!BC76,'COD. PROJETOS'!B:D,3,0),MID('BASE FINANCEIRO'!BI76,36,7),IF(VLOOKUP('BASE FINANCEIRO'!BC76,'COD. PROJETOS'!B:D,3,0),MID('BASE FINANCEIRO'!BI76,36,9),"PROJETO?"))) -> #N/A | E37: =VLOOKUP(D37,'BASE MUNICÍPIO'!B30:C24753,2,0) -> #N/A | F37: =VLOOKUP(D37,'BASE MUNICÍPIO'!B30:D24753,3,0) -> #N/A | G37: =IF(Tabela4[[#This Row],[PROJETO]]="CLARO",LEFT(Tabela4[[#This Row],[SITE2]],2),IF(Tabela4[[#This Row],[PROJETO]]="VIVO",RIGHT(LEFT(Tabela4[[#This Row],[SITE2]],10),2),""))
A38: ='BASE FINANCEIRO'!BI77 -> 0 | B38: =MID(A38,36,14) | C38: VIVO | D38: =IF(VLOOKUP('BASE FINANCEIRO'!BC77,'COD. PROJETOS'!B:D,3,0)="VIVO",MID('BASE FINANCEIRO'!BI77,36,3),IF(VLOOKUP('BASE FINANCEIRO'!BC77,'COD. PROJETOS'!B:D,3,0),MID('BASE FINANCEIRO'!BI77,36,7),IF(VLOOKUP('BASE FINANCEIRO'!BC77,'COD. PROJETOS'!B:D,3,0),MID('BASE FINANCEIRO'!BI77,36,9),"PROJETO?"))) -> #N/A | E38: =VLOOKUP(D38,'BASE MUNICÍPIO'!B31:C24754,2,0) -> #N/A | F38: =VLOOKUP(D38,'BASE MUNICÍPIO'!B31:D24754,3,0) -> #N/A | G38: =IF(Tabela4[[#This Row],[PROJETO]]="CLARO",LEFT(Tabela4[[#This Row],[SITE2]],2),IF(Tabela4[[#This Row],[PROJETO]]="VIVO",RIGHT(LEFT(Tabela4[[#This Row],[SITE2]],10),2),""))
A39: ='BASE FINANCEIRO'!BI78 -> 0 | B39: =MID(A39,36,14) | C39: VIVO | D39: =IF(VLOOKUP('BASE FINANCEIRO'!BC78,'COD. PROJETOS'!B:D,3,0)="VIVO",MID('BASE FINANCEIRO'!BI78,36,3),IF(VLOOKUP('BASE FINANCEIRO'!BC78,'COD. PROJETOS'!B:D,3,0),MID('BASE FINANCEIRO'!BI78,36,7),IF(VLOOKUP('BASE FINANCEIRO'!BC78,'COD. PROJETOS'!B:D,3,0),MID('BASE FINANCEIRO'!BI78,36,9),"PROJETO?"))) -> #N/A | E39: =VLOOKUP(D39,'BASE MUNICÍPIO'!B31:C24755,2,0) -> #N/A | F39: =VLOOKUP(D39,'BASE MUNICÍPIO'!B31:D24755,3,0) -> #N/A | G39: =IF(Tabela4[[#This Row],[PROJETO]]="CLARO",LEFT(Tabela4[[#This Row],[SITE2]],2),IF(Tabela4[[#This Row],[PROJETO]]="VIVO",RIGHT(LEFT(Tabela4[[#This Row],[SITE2]],10),2),""))
A40: ='BASE FINANCEIRO'!BI79 -> 0 | B40: =MID(A40,36,14) | C40: VIVO | D40: =IF(VLOOKUP('BASE FINANCEIRO'!BC79,'COD. PROJETOS'!B:D,3,0)="VIVO",MID('BASE FINANCEIRO'!BI79,36,3),IF(VLOOKUP('BASE FINANCEIRO'!BC79,'COD. PROJETOS'!B:D,3,0),MID('BASE FINANCEIRO'!BI79,36,7),IF(VLOOKUP('BASE FINANCEIRO'!BC79,'COD. PROJETOS'!B:D,3,0),MID('BASE FINANCEIRO'!BI79,36,9),"PROJETO?"))) -> #N/A | E40: =VLOOKUP(D40,'BASE MUNICÍPIO'!B31:C24756,2,0) -> #N/A | F40: =VLOOKUP(D40,'BASE MUNICÍPIO'!B31:D24756,3,0) -> #N/A | G40: =IF(Tabela4[[#This Row],[PROJETO]]="CLARO",LEFT(Tabela4[[#This Row],[SITE2]],2),IF(Tabela4[[#This Row],[PROJETO]]="VIVO",RIGHT(LEFT(Tabela4[[#This Row],[SITE2]],10),2),""))
A41: ='BASE FINANCEIRO'!BI80 -> 0 | B41: =MID(A41,36,14) | C41: VIVO | D41: =IF(VLOOKUP('BASE FINANCEIRO'!BC80,'COD. PROJETOS'!B:D,3,0)="VIVO",MID('BASE FINANCEIRO'!BI80,36,3),IF(VLOOKUP('BASE FINANCEIRO'!BC80,'COD. PROJETOS'!B:D,3,0),MID('BASE FINANCEIRO'!BI80,36,7),IF(VLOOKUP('BASE FINANCEIRO'!BC80,'COD. PROJETOS'!B:D,3,0),MID('BASE FINANCEIRO'!BI80,36,9),"PROJETO?"))) -> #N/A | E41: =VLOOKUP(D41,'BASE MUNICÍPIO'!B32:C24757,2,0) -> #N/A | F41: =VLOOKUP(D41,'BASE MUNICÍPIO'!B32:D24757,3,0) -> #N/A | G41: =IF(Tabela4[[#This Row],[PROJETO]]="CLARO",LEFT(Tabela4[[#This Row],[SITE2]],2),IF(Tabela4[[#This Row],[PROJETO]]="VIVO",RIGHT(LEFT(Tabela4[[#This Row],[SITE2]],10),2),""))
A42: ='BASE FINANCEIRO'!BI81 -> 0 | B42: =MID(A42,36,14) | C42: VIVO | D42: =IF(VLOOKUP('BASE FINANCEIRO'!BC81,'COD. PROJETOS'!B:D,3,0)="VIVO",MID('BASE FINANCEIRO'!BI81,36,3),IF(VLOOKUP('BASE FINANCEIRO'!BC81,'COD. PROJETOS'!B:D,3,0),MID('BASE FINANCEIRO'!BI81,36,7),IF(VLOOKUP('BASE FINANCEIRO'!BC81,'COD. PROJETOS'!B:D,3,0),MID('BASE FINANCEIRO'!BI81,36,9),"PROJETO?"))) -> #N/A | E42: =VLOOKUP(D42,'BASE MUNICÍPIO'!B33:C24758,2,0) -> #N/A | F42: =VLOOKUP(D42,'BASE MUNICÍPIO'!B33:D24758,3,0) -> #N/A | G42: =IF(Tabela4[[#This Row],[PROJETO]]="CLARO",LEFT(Tabela4[[#This Row],[SITE2]],2),IF(Tabela4[[#This Row],[PROJETO]]="VIVO",RIGHT(LEFT(Tabela4[[#This Row],[SITE2]],10),2),""))
A43: ='BASE FINANCEIRO'!BI82 -> 0 | B43: =MID(A43,36,14) | C43: VIVO | D43: =IF(VLOOKUP('BASE FINANCEIRO'!BC82,'COD. PROJETOS'!B:D,3,0)="VIVO",MID('BASE FINANCEIRO'!BI82,36,3),IF(VLOOKUP('BASE FINANCEIRO'!BC82,'COD. PROJETOS'!B:D,3,0),MID('BASE FINANCEIRO'!BI82,36,7),IF(VLOOKUP('BASE FINANCEIRO'!BC82,'COD. PROJETOS'!B:D,3,0),MID('BASE FINANCEIRO'!BI82,36,9),"PROJETO?"))) -> #N/A | E43: =VLOOKUP(D43,'BASE MUNICÍPIO'!B33:C24759,2,0) -> #N/A | F43: =VLOOKUP(D43,'BASE MUNICÍPIO'!B33:D24759,3,0) -> #N/A | G43: =IF(Tabela4[[#This Row],[PROJETO]]="CLARO",LEFT(Tabela4[[#This Row],[SITE2]],2),IF(Tabela4[[#This Row],[PROJETO]]="VIVO",RIGHT(LEFT(Tabela4[[#This Row],[SITE2]],10),2),""))
A44: ='BASE FINANCEIRO'!BI83 -> 0 | B44: =MID(A44,36,14) | C44: VIVO | D44: =IF(VLOOKUP('BASE FINANCEIRO'!BC83,'COD. PROJETOS'!B:D,3,0)="VIVO",MID('BASE FINANCEIRO'!BI83,36,3),IF(VLOOKUP('BASE FINANCEIRO'!BC83,'COD. PROJETOS'!B:D,3,0),MID('BASE FINANCEIRO'!BI83,36,7),IF(VLOOKUP('BASE FINANCEIRO'!BC83,'COD. PROJETOS'!B:D,3,0),MID('BASE FINANCEIRO'!BI83,36,9),"PROJETO?"))) -> #N/A | E44: =VLOOKUP(D44,'BASE MUNICÍPIO'!B34:C24760,2,0) -> #N/A | F44: =VLOOKUP(D44,'BASE MUNICÍPIO'!B34:D24760,3,0) -> #N/A | G44: =IF(Tabela4[[#This Row],[PROJETO]]="CLARO",LEFT(Tabela4[[#This Row],[SITE2]],2),IF(Tabela4[[#This Row],[PROJETO]]="VIVO",RIGHT(LEFT(Tabela4[[#This Row],[SITE2]],10),2),""))
A45: ='BASE FINANCEIRO'!BI84 -> 0 | B45: =MID(A45,36,14) | C45: VIVO | D45: =IF(VLOOKUP('BASE FINANCEIRO'!BC84,'COD. PROJETOS'!B:D,3,0)="VIVO",MID('BASE FINANCEIRO'!BI84,36,3),IF(VLOOKUP('BASE FINANCEIRO'!BC84,'COD. PROJETOS'!B:D,3,0),MID('BASE FINANCEIRO'!BI84,36,7),IF(VLOOKUP('BASE FINANCEIRO'!BC84,'COD. PROJETOS'!B:D,3,0),MID('BASE FINANCEIRO'!BI84,36,9),"PROJETO?"))) -> #N/A | E45: =VLOOKUP(D45,'BASE MUNICÍPIO'!B35:C24761,2,0) -> #N/A | F45: =VLOOKUP(D45,'BASE MUNICÍPIO'!B35:D24761,3,0) -> #N/A | G45: =IF(Tabela4[[#This Row],[PROJETO]]="CLARO",LEFT(Tabela4[[#This Row],[SITE2]],2),IF(Tabela4[[#This Row],[PROJETO]]="VIVO",RIGHT(LEFT(Tabela4[[#This Row],[SITE2]],10),2),""))
A46: ='BASE FINANCEIRO'!BI85 -> 0 | B46: =MID(A46,36,14) | C46: VIVO | D46: =IF(VLOOKUP('BASE FINANCEIRO'!BC85,'COD. PROJETOS'!B:D,3,0)="VIVO",MID('BASE FINANCEIRO'!BI85,36,3),IF(VLOOKUP('BASE FINANCEIRO'!BC85,'COD. PROJETOS'!B:D,3,0),MID('BASE FINANCEIRO'!BI85,36,7),IF(VLOOKUP('BASE FINANCEIRO'!BC85,'COD. PROJETOS'!B:D,3,0),MID('BASE FINANCEIRO'!BI85,36,9),"PROJETO?"))) -> #N/A | E46: =VLOOKUP(D46,'BASE MUNICÍPIO'!B36:C24762,2,0) -> #N/A | F46: =VLOOKUP(D46,'BASE MUNICÍPIO'!B36:D24762,3,0) -> #N/A | G46: =IF(Tabela4[[#This Row],[PROJETO]]="CLARO",LEFT(Tabela4[[#This Row],[SITE2]],2),IF(Tabela4[[#This Row],[PROJETO]]="VIVO",RIGHT(LEFT(Tabela4[[#This Row],[SITE2]],10),2),""))
A47: ='BASE FINANCEIRO'!BI86 -> 0 | B47: =MID(A47,36,14) | C47: VIVO | D47: =IF(VLOOKUP('BASE FINANCEIRO'!BC86,'COD. PROJETOS'!B:D,3,0)="VIVO",MID('BASE FINANCEIRO'!BI86,36,3),IF(VLOOKUP('BASE FINANCEIRO'!BC86,'COD. PROJETOS'!B:D,3,0),MID('BASE FINANCEIRO'!BI86,36,7),IF(VLOOKUP('BASE FINANCEIRO'!BC86,'COD. PROJETOS'!B:D,3,0),MID('BASE FINANCEIRO'!BI86,36,9),"PROJETO?"))) -> #N/A | E47: =VLOOKUP(D47,'BASE MUNICÍPIO'!B36:C24763,2,0) -> #N/A | F47: =VLOOKUP(D47,'BASE MUNICÍPIO'!B36:D24763,3,0) -> #N/A | G47: =IF(Tabela4[[#This Row],[PROJETO]]="CLARO",LEFT(Tabela4[[#This Row],[SITE2]],2),IF(Tabela4[[#This Row],[PROJETO]]="VIVO",RIGHT(LEFT(Tabela4[[#This Row],[SITE2]],10),2),""))
A48: ='BASE FINANCEIRO'!BI87 -> 0 | B48: =MID(A48,36,14) | C48: VIVO | D48: =IF(VLOOKUP('BASE FINANCEIRO'!BC87,'COD. PROJETOS'!B:D,3,0)="VIVO",MID('BASE FINANCEIRO'!BI87,36,3),IF(VLOOKUP('BASE FINANCEIRO'!BC87,'COD. PROJETOS'!B:D,3,0),MID('BASE FINANCEIRO'!BI87,36,7),IF(VLOOKUP('BASE FINANCEIRO'!BC87,'COD. PROJETOS'!B:D,3,0),MID('BASE FINANCEIRO'!BI87,36,9),"PROJETO?"))) -> #N/A | E48: =VLOOKUP(D48,'BASE MUNICÍPIO'!B36:C24764,2,0) -> #N/A | F48: =VLOOKUP(D48,'BASE MUNICÍPIO'!B36:D24764,3,0) -> #N/A | G48: =IF(Tabela4[[#This Row],[PROJETO]]="CLARO",LEFT(Tabela4[[#This Row],[SITE2]],2),IF(Tabela4[[#This Row],[PROJETO]]="VIVO",RIGHT(LEFT(Tabela4[[#This Row],[SITE2]],10),2),""))
A49: ='BASE FINANCEIRO'!BI88 -> 0 | B49: =MID(A49,36,14) | C49: VIVO | D49: =IF(VLOOKUP('BASE FINANCEIRO'!BC88,'COD. PROJETOS'!B:D,3,0)="VIVO",MID('BASE FINANCEIRO'!BI88,36,3),IF(VLOOKUP('BASE FINANCEIRO'!BC88,'COD. PROJETOS'!B:D,3,0),MID('BASE FINANCEIRO'!BI88,36,7),IF(VLOOKUP('BASE FINANCEIRO'!BC88,'COD. PROJETOS'!B:D,3,0),MID('BASE FINANCEIRO'!BI88,36,9),"PROJETO?"))) -> #N/A | E49: =VLOOKUP(D49,'BASE MUNICÍPIO'!B37:C24765,2,0) -> #N/A | F49: =VLOOKUP(D49,'BASE MUNICÍPIO'!B37:D24765,3,0) -> #N/A | G49: =IF(Tabela4[[#This Row],[PROJETO]]="CLARO",LEFT(Tabela4[[#This Row],[SITE2]],2),IF(Tabela4[[#This Row],[PROJETO]]="VIVO",RIGHT(LEFT(Tabela4[[#This Row],[SITE2]],10),2),""))
A50: ='BASE FINANCEIRO'!BI89 -> 0 | B50: =MID(A50,36,14) | C50: VIVO | D50: =IF(VLOOKUP('BASE FINANCEIRO'!BC89,'COD. PROJETOS'!B:D,3,0)="VIVO",MID('BASE FINANCEIRO'!BI89,36,3),IF(VLOOKUP('BASE FINANCEIRO'!BC89,'COD. PROJETOS'!B:D,3,0),MID('BASE FINANCEIRO'!BI89,36,7),IF(VLOOKUP('BASE FINANCEIRO'!BC89,'COD. PROJETOS'!B:D,3,0),MID('BASE FINANCEIRO'!BI89,36,9),"PROJETO?"))) -> #N/A | E50: =VLOOKUP(D50,'BASE MUNICÍPIO'!B37:C24766,2,0) -> #N/A | F50: =VLOOKUP(D50,'BASE MUNICÍPIO'!B37:D24766,3,0) -> #N/A | G50: =IF(Tabela4[[#This Row],[PROJETO]]="CLARO",LEFT(Tabela4[[#This Row],[SITE2]],2),IF(Tabela4[[#This Row],[PROJETO]]="VIVO",RIGHT(LEFT(Tabela4[[#This Row],[SITE2]],10),2),""))
A51: ='BASE FINANCEIRO'!BI90 -> 0 | B51: =MID(A51,36,14) | C51: VIVO | D51: =IF(VLOOKUP('BASE FINANCEIRO'!BC90,'COD. PROJETOS'!B:D,3,0)="VIVO",MID('BASE FINANCEIRO'!BI90,36,3),IF(VLOOKUP('BASE FINANCEIRO'!BC90,'COD. PROJETOS'!B:D,3,0),MID('BASE FINANCEIRO'!BI90,36,7),IF(VLOOKUP('BASE FINANCEIRO'!BC90,'COD. PROJETOS'!B:D,3,0),MID('BASE FINANCEIRO'!BI90,36,9),"PROJETO?"))) -> #N/A | E51: =VLOOKUP(D51,'BASE MUNICÍPIO'!B38:C24767,2,0) -> #N/A | F51: =VLOOKUP(D51,'BASE MUNICÍPIO'!B38:D24767,3,0) -> #N/A | G51: =IF(Tabela4[[#This Row],[PROJETO]]="CLARO",LEFT(Tabela4[[#This Row],[SITE2]],2),IF(Tabela4[[#This Row],[PROJETO]]="VIVO",RIGHT(LEFT(Tabela4[[#This Row],[SITE2]],10),2),""))
A52: ='BASE FINANCEIRO'!BI91 -> 0 | B52: =MID(A52,36,14) | C52: VIVO | D52: =IF(VLOOKUP('BASE FINANCEIRO'!BC91,'COD. PROJETOS'!B:D,3,0)="VIVO",MID('BASE FINANCEIRO'!BI91,36,3),IF(VLOOKUP('BASE FINANCEIRO'!BC91,'COD. PROJETOS'!B:D,3,0),MID('BASE FINANCEIRO'!BI91,36,7),IF(VLOOKUP('BASE FINANCEIRO'!BC91,'COD. PROJETOS'!B:D,3,0),MID('BASE FINANCEIRO'!BI91,36,9),"PROJETO?"))) -> #N/A | E52: =VLOOKUP(D52,'BASE MUNICÍPIO'!B39:C24768,2,0) -> #N/A | F52: =VLOOKUP(D52,'BASE MUNICÍPIO'!B39:D24768,3,0) -> #N/A | G52: =IF(Tabela4[[#This Row],[PROJETO]]="CLARO",LEFT(Tabela4[[#This Row],[SITE2]],2),IF(Tabela4[[#This Row],[PROJETO]]="VIVO",RIGHT(LEFT(Tabela4[[#This Row],[SITE2]],10),2),""))
A53: ='BASE FINANCEIRO'!BI92 -> 0 | B53: =MID(A53,36,14) | C53: VIVO | D53: =IF(VLOOKUP('BASE FINANCEIRO'!BC92,'COD. PROJETOS'!B:D,3,0)="VIVO",MID('BASE FINANCEIRO'!BI92,36,3),IF(VLOOKUP('BASE FINANCEIRO'!BC92,'COD. PROJETOS'!B:D,3,0),MID('BASE FINANCEIRO'!BI92,36,7),IF(VLOOKUP('BASE FINANCEIRO'!BC92,'COD. PROJETOS'!B:D,3,0),MID('BASE FINANCEIRO'!BI92,36,9),"PROJETO?"))) -> #N/A | E53: =VLOOKUP(D53,'BASE MUNICÍPIO'!B39:C24769,2,0) -> #N/A | F53: =VLOOKUP(D53,'BASE MUNICÍPIO'!B39:D24769,3,0) -> #N/A | G53: =IF(Tabela4[[#This Row],[PROJETO]]="CLARO",LEFT(Tabela4[[#This Row],[SITE2]],2),IF(Tabela4[[#This Row],[PROJETO]]="VIVO",RIGHT(LEFT(Tabela4[[#This Row],[SITE2]],10),2),""))
A54: ='BASE FINANCEIRO'!BI93 -> 0 | B54: =MID(A54,36,14) | C54: VIVO | D54: =IF(VLOOKUP('BASE FINANCEIRO'!BC93,'COD. PROJETOS'!B:D,3,0)="VIVO",MID('BASE FINANCEIRO'!BI93,36,3),IF(VLOOKUP('BASE FINANCEIRO'!BC93,'COD. PROJETOS'!B:D,3,0),MID('BASE FINANCEIRO'!BI93,36,7),IF(VLOOKUP('BASE FINANCEIRO'!BC93,'COD. PROJETOS'!B:D,3,0),MID('BASE FINANCEIRO'!BI93,36,9),"PROJETO?"))) -> #N/A | E54: =VLOOKUP(D54,'BASE MUNICÍPIO'!B40:C24770,2,0) -> #N/A | F54: =VLOOKUP(D54,'BASE MUNICÍPIO'!B40:D24770,3,0) -> #N/A | G54: =IF(Tabela4[[#This Row],[PROJETO]]="CLARO",LEFT(Tabela4[[#This Row],[SITE2]],2),IF(Tabela4[[#This Row],[PROJETO]]="VIVO",RIGHT(LEFT(Tabela4[[#This Row],[SITE2]],10),2),""))
A55: ='BASE FINANCEIRO'!BI94 -> 0 | B55: =MID(A55,36,14) | C55: VIVO | D55: =IF(VLOOKUP('BASE FINANCEIRO'!BC94,'COD. PROJETOS'!B:D,3,0)="VIVO",MID('BASE FINANCEIRO'!BI94,36,3),IF(VLOOKUP('BASE FINANCEIRO'!BC94,'COD. PROJETOS'!B:D,3,0),MID('BASE FINANCEIRO'!BI94,36,7),IF(VLOOKUP('BASE FINANCEIRO'!BC94,'COD. PROJETOS'!B:D,3,0),MID('BASE FINANCEIRO'!BI94,36,9),"PROJETO?"))) -> #N/A | E55: =VLOOKUP(D55,'BASE MUNICÍPIO'!B40:C24771,2,0) -> #N/A | F55: =VLOOKUP(D55,'BASE MUNICÍPIO'!B40:D24771,3,0) -> #N/A | G55: =IF(Tabela4[[#This Row],[PROJETO]]="CLARO",LEFT(Tabela4[[#This Row],[SITE2]],2),IF(Tabela4[[#This Row],[PROJETO]]="VIVO",RIGHT(LEFT(Tabela4[[#This Row],[SITE2]],10),2),""))
A56: ='BASE FINANCEIRO'!BI95 -> 0 | B56: =MID(A56,36,14) | C56: VIVO | D56: =IF(VLOOKUP('BASE FINANCEIRO'!BC95,'COD. PROJETOS'!B:D,3,0)="VIVO",MID('BASE FINANCEIRO'!BI95,36,3),IF(VLOOKUP('BASE FINANCEIRO'!BC95,'COD. PROJETOS'!B:D,3,0),MID('BASE FINANCEIRO'!BI95,36,7),IF(VLOOKUP('BASE FINANCEIRO'!BC95,'COD. PROJETOS'!B:D,3,0),MID('BASE FINANCEIRO'!BI95,36,9),"PROJETO?"))) -> #N/A | E56: =VLOOKUP(D56,'BASE MUNICÍPIO'!B41:C24772,2,0) -> #N/A | F56: =VLOOKUP(D56,'BASE MUNICÍPIO'!B41:D24772,3,0) -> #N/A | G56: =IF(Tabela4[[#This Row],[PROJETO]]="CLARO",LEFT(Tabela4[[#This Row],[SITE2]],2),IF(Tabela4[[#This Row],[PROJETO]]="VIVO",RIGHT(LEFT(Tabela4[[#This Row],[SITE2]],10),2),""))
A57: ='BASE FINANCEIRO'!BI96 -> 0 | B57: =MID(A57,36,14) | C57: VIVO | D57: =IF(VLOOKUP('BASE FINANCEIRO'!BC96,'COD. PROJETOS'!B:D,3,0)="VIVO",MID('BASE FINANCEIRO'!BI96,36,3),IF(VLOOKUP('BASE FINANCEIRO'!BC96,'COD. PROJETOS'!B:D,3,0),MID('BASE FINANCEIRO'!BI96,36,7),IF(VLOOKUP('BASE FINANCEIRO'!BC96,'COD. PROJETOS'!B:D,3,0),MID('BASE FINANCEIRO'!BI96,36,9),"PROJETO?"))) -> #N/A | E57: =VLOOKUP(D57,'BASE MUNICÍPIO'!B41:C24773,2,0) -> #N/A | F57: =VLOOKUP(D57,'BASE MUNICÍPIO'!B41:D24773,3,0) -> #N/A | G57: =IF(Tabela4[[#This Row],[PROJETO]]="CLARO",LEFT(Tabela4[[#This Row],[SITE2]],2),IF(Tabela4[[#This Row],[PROJETO]]="VIVO",RIGHT(LEFT(Tabela4[[#This Row],[SITE2]],10),2),""))
A58: ='BASE FINANCEIRO'!BI97 -> 0 | B58: =MID(A58,36,14) | C58: VIVO | D58: =IF(VLOOKUP('BASE FINANCEIRO'!BC97,'COD. PROJETOS'!B:D,3,0)="VIVO",MID('BASE FINANCEIRO'!BI97,36,3),IF(VLOOKUP('BASE FINANCEIRO'!BC97,'COD. PROJETOS'!B:D,3,0),MID('BASE FINANCEIRO'!BI97,36,7),IF(VLOOKUP('BASE FINANCEIRO'!BC97,'COD. PROJETOS'!B:D,3,0),MID('BASE FINANCEIRO'!BI97,36,9),"PROJETO?"))) -> #N/A | E58: =VLOOKUP(D58,'BASE MUNICÍPIO'!B42:C24774,2,0) -> #N/A | F58: =VLOOKUP(D58,'BASE MUNICÍPIO'!B42:D24774,3,0) -> #N/A | G58: =IF(Tabela4[[#This Row],[PROJETO]]="CLARO",LEFT(Tabela4[[#This Row],[SITE2]],2),IF(Tabela4[[#This Row],[PROJETO]]="VIVO",RIGHT(LEFT(Tabela4[[#This Row],[SITE2]],10),2),""))
A59: ='BASE FINANCEIRO'!BI98 -> 0 | B59: =MID(A59,36,14) | C59: VIVO | D59: =IF(VLOOKUP('BASE FINANCEIRO'!BC99,'COD. PROJETOS'!B:D,3,0)="VIVO",MID('BASE FINANCEIRO'!BI98,36,3),IF(VLOOKUP('BASE FINANCEIRO'!BC99,'COD. PROJETOS'!B:D,3,0),MID('BASE FINANCEIRO'!BI98,36,7),IF(VLOOKUP('BASE FINANCEIRO'!BC99,'COD. PROJETOS'!B:D,3,0),MID('BASE FINANCEIRO'!BI98,36,9),"PROJETO?"))) -> #N/A | E59: =VLOOKUP(D59,'BASE MUNICÍPIO'!B42:C24775,2,0) -> #N/A | F59: =VLOOKUP(D59,'BASE MUNICÍPIO'!B42:D24775,3,0) -> #N/A | G59: =IF(Tabela4[[#This Row],[PROJETO]]="CLARO",LEFT(Tabela4[[#This Row],[SITE2]],2),IF(Tabela4[[#This Row],[PROJETO]]="VIVO",RIGHT(LEFT(Tabela4[[#This Row],[SITE2]],10),2),""))
A60: ='BASE FINANCEIRO'!BI99 -> 0 | B60: =MID(A60,36,14) | C60: VIVO | D60: =IF(VLOOKUP('BASE FINANCEIRO'!#REF!,'COD. PROJETOS'!B:D,3,0)="VIVO",MID('BASE FINANCEIRO'!BI99,36,3),IF(VLOOKUP('BASE FINANCEIRO'!#REF!,'COD. PROJETOS'!B:D,3,0),MID('BASE FINANCEIRO'!BI99,36,7),IF(VLOOKUP('BASE FINANCEIRO'!#REF!,'COD. PROJETOS'!B:D,3,0),MID('BASE FINANCEIRO'!BI99,36,9),"PROJETO?"))) -> #REF! | E60: =VLOOKUP(D60,'BASE MUNICÍPIO'!B43:C24776,2,0) -> #REF! | F60: =VLOOKUP(D60,'BASE MUNICÍPIO'!B43:D24776,3,0) -> #REF! | G60: =IF(Tabela4[[#This Row],[PROJETO]]="CLARO",LEFT(Tabela4[[#This Row],[SITE2]],2),IF(Tabela4[[#This Row],[PROJETO]]="VIVO",RIGHT(LEFT(Tabela4[[#This Row],[SITE2]],10),2),""))
A61: ='BASE FINANCEIRO'!BI100 -> 0 | B61: =MID(A61,36,14) | C61: VIVO | D61: =IF(VLOOKUP('BASE FINANCEIRO'!BC100,'COD. PROJETOS'!B:D,3,0)="VIVO",MID('BASE FINANCEIRO'!BI100,36,3),IF(VLOOKUP('BASE FINANCEIRO'!BC100,'COD. PROJETOS'!B:D,3,0),MID('BASE FINANCEIRO'!BI100,36,7),IF(VLOOKUP('BASE FINANCEIRO'!BC100,'COD. PROJETOS'!B:D,3,0),MID('BASE FINANCEIRO'!BI100,36,9),"PROJETO?"))) -> #N/A | E61: =VLOOKUP(D61,'BASE MUNICÍPIO'!B44:C24777,2,0) -> #N/A | F61: =VLOOKUP(D61,'BASE MUNICÍPIO'!B44:D24777,3,0) -> #N/A | G61: =IF(Tabela4[[#This Row],[PROJETO]]="CLARO",LEFT(Tabela4[[#This Row],[SITE2]],2),IF(Tabela4[[#This Row],[PROJETO]]="VIVO",RIGHT(LEFT(Tabela4[[#This Row],[SITE2]],10),2),""))
A62: ='BASE FINANCEIRO'!BI101 -> 0 | B62: =MID(A62,36,14) | C62: VIVO | D62: =IF(VLOOKUP('BASE FINANCEIRO'!BC101,'COD. PROJETOS'!B:D,3,0)="VIVO",MID('BASE FINANCEIRO'!BI101,36,3),IF(VLOOKUP('BASE FINANCEIRO'!BC101,'COD. PROJETOS'!B:D,3,0),MID('BASE FINANCEIRO'!BI101,36,7),IF(VLOOKUP('BASE FINANCEIRO'!BC101,'COD. PROJETOS'!B:D,3,0),MID('BASE FINANCEIRO'!BI101,36,9),"PROJETO?"))) -> #N/A | E62: =VLOOKUP(D62,'BASE MUNICÍPIO'!B44:C24778,2,0) -> #N/A | F62: =VLOOKUP(D62,'BASE MUNICÍPIO'!B44:D24778,3,0) -> #N/A | G62: =IF(Tabela4[[#This Row],[PROJETO]]="CLARO",LEFT(Tabela4[[#This Row],[SITE2]],2),IF(Tabela4[[#This Row],[PROJETO]]="VIVO",RIGHT(LEFT(Tabela4[[#This Row],[SITE2]],10),2),""))
A63: ='BASE FINANCEIRO'!BI102 -> 0 | B63: =MID(A63,36,14) | C63: VIVO | D63: =IF(VLOOKUP('BASE FINANCEIRO'!BC102,'COD. PROJETOS'!B:D,3,0)="VIVO",MID('BASE FINANCEIRO'!BI102,36,3),IF(VLOOKUP('BASE FINANCEIRO'!BC102,'COD. PROJETOS'!B:D,3,0),MID('BASE FINANCEIRO'!BI102,36,7),IF(VLOOKUP('BASE FINANCEIRO'!BC102,'COD. PROJETOS'!B:D,3,0),MID('BASE FINANCEIRO'!BI102,36,9),"PROJETO?"))) -> #N/A | E63: =VLOOKUP(D63,'BASE MUNICÍPIO'!B45:C24779,2,0) -> #N/A | F63: =VLOOKUP(D63,'BASE MUNICÍPIO'!B45:D24779,3,0) -> #N/A | G63: =IF(Tabela4[[#This Row],[PROJETO]]="CLARO",LEFT(Tabela4[[#This Row],[SITE2]],2),IF(Tabela4[[#This Row],[PROJETO]]="VIVO",RIGHT(LEFT(Tabela4[[#This Row],[SITE2]],10),2),""))
A64: ='BASE FINANCEIRO'!BI103 -> 0 | B64: =MID(A64,36,14) | C64: VIVO | D64: =IF(VLOOKUP('BASE FINANCEIRO'!BC103,'COD. PROJETOS'!B:D,3,0)="VIVO",MID('BASE FINANCEIRO'!BI103,36,3),IF(VLOOKUP('BASE FINANCEIRO'!BC103,'COD. PROJETOS'!B:D,3,0),MID('BASE FINANCEIRO'!BI103,36,7),IF(VLOOKUP('BASE FINANCEIRO'!BC103,'COD. PROJETOS'!B:D,3,0),MID('BASE FINANCEIRO'!BI103,36,9),"PROJETO?"))) -> #N/A | E64: =VLOOKUP(D64,'BASE MUNICÍPIO'!B45:C24780,2,0) -> #N/A | F64: =VLOOKUP(D64,'BASE MUNICÍPIO'!B45:D24780,3,0) -> #N/A | G64: =IF(Tabela4[[#This Row],[PROJETO]]="CLARO",LEFT(Tabela4[[#This Row],[SITE2]],2),IF(Tabela4[[#This Row],[PROJETO]]="VIVO",RIGHT(LEFT(Tabela4[[#This Row],[SITE2]],10),2),""))
A65: ='BASE FINANCEIRO'!#REF! -> #REF! | B65: =MID(A65,36,14) -> #REF! | C65: VIVO | D65: =IF(VLOOKUP('BASE FINANCEIRO'!#REF!,'COD. PROJETOS'!B:D,3,0)="VIVO",MID('BASE FINANCEIRO'!#REF!,36,3),IF(VLOOKUP('BASE FINANCEIRO'!#REF!,'COD. PROJETOS'!B:D,3,0),MID('BASE FINANCEIRO'!#REF!,36,7),IF(VLOOKUP('BASE FINANCEIRO'!#REF!,'COD. PROJETOS'!B:D,3,0),MID('BASE FINANCEIRO'!#REF!,36,9),"PROJETO?"))) -> #REF! | E65: =VLOOKUP(D65,'BASE MUNICÍPIO'!B46:C24781,2,0) -> #REF! | F65: =VLOOKUP(D65,'BASE MUNICÍPIO'!B46:D24781,3,0) -> #REF! | G65: =IF(Tabela4[[#This Row],[PROJETO]]="CLARO",LEFT(Tabela4[[#This Row],[SITE2]],2),IF(Tabela4[[#This Row],[PROJETO]]="VIVO",RIGHT(LEFT(Tabela4[[#This Row],[SITE2]],10),2),"")) -> #REF!
A66: ='BASE FINANCEIRO'!BI104 -> 0 | B66: =MID(A66,36,14) | C66: VIVO | D66: =IF(VLOOKUP('BASE FINANCEIRO'!BC104,'COD. PROJETOS'!B:D,3,0)="VIVO",MID('BASE FINANCEIRO'!BI104,36,3),IF(VLOOKUP('BASE FINANCEIRO'!BC104,'COD. PROJETOS'!B:D,3,0),MID('BASE FINANCEIRO'!BI104,36,7),IF(VLOOKUP('BASE FINANCEIRO'!BC104,'COD. PROJETOS'!B:D,3,0),MID('BASE FINANCEIRO'!BI104,36,9),"PROJETO?"))) -> #N/A | E66: =VLOOKUP(D66,'BASE MUNICÍPIO'!B47:C24782,2,0) -> #N/A | F66: =VLOOKUP(D66,'BASE MUNICÍPIO'!B47:D24782,3,0) -> #N/A | G66: =IF(Tabela4[[#This Row],[PROJETO]]="CLARO",LEFT(Tabela4[[#This Row],[SITE2]],2),IF(Tabela4[[#This Row],[PROJETO]]="VIVO",RIGHT(LEFT(Tabela4[[#This Row],[SITE2]],10),2),""))
A67: ='BASE FINANCEIRO'!BI105 -> 0 | B67: =MID(A67,36,14) | C67: VIVO | D67: =IF(VLOOKUP('BASE FINANCEIRO'!BC105,'COD. PROJETOS'!B:D,3,0)="VIVO",MID('BASE FINANCEIRO'!BI105,36,3),IF(VLOOKUP('BASE FINANCEIRO'!BC105,'COD. PROJETOS'!B:D,3,0),MID('BASE FINANCEIRO'!BI105,36,7),IF(VLOOKUP('BASE FINANCEIRO'!BC105,'COD. PROJETOS'!B:D,3,0),MID('BASE FINANCEIRO'!BI105,36,9),"PROJETO?"))) -> #N/A | E67: =VLOOKUP(D67,'BASE MUNICÍPIO'!B48:C24783,2,0) -> #N/A | F67: =VLOOKUP(D67,'BASE MUNICÍPIO'!B48:D24783,3,0) -> #N/A | G67: =IF(Tabela4[[#This Row],[PROJETO]]="CLARO",LEFT(Tabela4[[#This Row],[SITE2]],2),IF(Tabela4[[#This Row],[PROJETO]]="VIVO",RIGHT(LEFT(Tabela4[[#This Row],[SITE2]],10),2),""))
A68: ='BASE FINANCEIRO'!BI106 -> 0 | B68: =MID(A68,36,14) | C68: VIVO | D68: =IF(VLOOKUP('BASE FINANCEIRO'!BC106,'COD. PROJETOS'!B:D,3,0)="VIVO",MID('BASE FINANCEIRO'!BI106,36,3),IF(VLOOKUP('BASE FINANCEIRO'!BC106,'COD. PROJETOS'!B:D,3,0),MID('BASE FINANCEIRO'!BI106,36,7),IF(VLOOKUP('BASE FINANCEIRO'!BC106,'COD. PROJETOS'!B:D,3,0),MID('BASE FINANCEIRO'!BI106,36,9),"PROJETO?"))) -> #N/A | E68: =VLOOKUP(D68,'BASE MUNICÍPIO'!B49:C24784,2,0) -> #N/A | F68: =VLOOKUP(D68,'BASE MUNICÍPIO'!B49:D24784,3,0) -> #N/A | G68: =IF(Tabela4[[#This Row],[PROJETO]]="CLARO",LEFT(Tabela4[[#This Row],[SITE2]],2),IF(Tabela4[[#This Row],[PROJETO]]="VIVO",RIGHT(LEFT(Tabela4[[#This Row],[SITE2]],10),2),""))
A69: ='BASE FINANCEIRO'!BI107 -> 0 | B69: =MID(A69,36,14) | C69: VIVO | D69: =IF(VLOOKUP('BASE FINANCEIRO'!BC107,'COD. PROJETOS'!B:D,3,0)="VIVO",MID('BASE FINANCEIRO'!BI107,36,3),IF(VLOOKUP('BASE FINANCEIRO'!BC107,'COD. PROJETOS'!B:D,3,0),MID('BASE FINANCEIRO'!BI107,36,7),IF(VLOOKUP('BASE FINANCEIRO'!BC107,'COD. PROJETOS'!B:D,3,0),MID('BASE FINANCEIRO'!BI107,36,9),"PROJETO?"))) -> #N/A | E69: =VLOOKUP(D69,'BASE MUNICÍPIO'!B50:C24785,2,0) -> #N/A | F69: =VLOOKUP(D69,'BASE MUNICÍPIO'!B50:D24785,3,0) -> #N/A | G69: =IF(Tabela4[[#This Row],[PROJETO]]="CLARO",LEFT(Tabela4[[#This Row],[SITE2]],2),IF(Tabela4[[#This Row],[PROJETO]]="VIVO",RIGHT(LEFT(Tabela4[[#This Row],[SITE2]],10),2),""))
A70: ='BASE FINANCEIRO'!BI108 -> 0 | B70: =MID(A70,36,14) | C70: VIVO | D70: =IF(VLOOKUP('BASE FINANCEIRO'!BC108,'COD. PROJETOS'!B:D,3,0)="VIVO",MID('BASE FINANCEIRO'!BI108,36,3),IF(VLOOKUP('BASE FINANCEIRO'!BC108,'COD. PROJETOS'!B:D,3,0),MID('BASE FINANCEIRO'!BI108,36,7),IF(VLOOKUP('BASE FINANCEIRO'!BC108,'COD. PROJETOS'!B:D,3,0),MID('BASE FINANCEIRO'!BI108,36,9),"PROJETO?"))) -> #N/A | E70: =VLOOKUP(D70,'BASE MUNICÍPIO'!B51:C24786,2,0) -> #N/A | F70: =VLOOKUP(D70,'BASE MUNICÍPIO'!B51:D24786,3,0) -> #N/A | G70: =IF(Tabela4[[#This Row],[PROJETO]]="CLARO",LEFT(Tabela4[[#This Row],[SITE2]],2),IF(Tabela4[[#This Row],[PROJETO]]="VIVO",RIGHT(LEFT(Tabela4[[#This Row],[SITE2]],10),2),""))
A71: ='BASE FINANCEIRO'!BI109 -> 0 | B71: =MID(A71,36,14) | C71: VIVO | D71: =IF(VLOOKUP('BASE FINANCEIRO'!BC109,'COD. PROJETOS'!B:D,3,0)="VIVO",MID('BASE FINANCEIRO'!BI109,36,3),IF(VLOOKUP('BASE FINANCEIRO'!BC109,'COD. PROJETOS'!B:D,3,0),MID('BASE FINANCEIRO'!BI109,36,7),IF(VLOOKUP('BASE FINANCEIRO'!BC109,'COD. PROJETOS'!B:D,3,0),MID('BASE FINANCEIRO'!BI109,36,9),"PROJETO?"))) -> #N/A | E71: =VLOOKUP(D71,'BASE MUNICÍPIO'!B52:C24787,2,0) -> #N/A | F71: =VLOOKUP(D71,'BASE MUNICÍPIO'!B52:D24787,3,0) -> #N/A | G71: =IF(Tabela4[[#This Row],[PROJETO]]="CLARO",LEFT(Tabela4[[#This Row],[SITE2]],2),IF(Tabela4[[#This Row],[PROJETO]]="VIVO",RIGHT(LEFT(Tabela4[[#This Row],[SITE2]],10),2),""))
A72: ='BASE FINANCEIRO'!BI110 -> 0 | B72: =MID(A72,36,14) | C72: VIVO | D72: =IF(VLOOKUP('BASE FINANCEIRO'!BC110,'COD. PROJETOS'!B:D,3,0)="VIVO",MID('BASE FINANCEIRO'!BI110,36,3),IF(VLOOKUP('BASE FINANCEIRO'!BC110,'COD. PROJETOS'!B:D,3,0),MID('BASE FINANCEIRO'!BI110,36,7),IF(VLOOKUP('BASE FINANCEIRO'!BC110,'COD. PROJETOS'!B:D,3,0),MID('BASE FINANCEIRO'!BI110,36,9),"PROJETO?"))) -> #N/A | E72: =VLOOKUP(D72,'BASE MUNICÍPIO'!B53:C24788,2,0) -> #N/A | F72: =VLOOKUP(D72,'BASE MUNICÍPIO'!B53:D24788,3,0) -> #N/A | G72: =IF(Tabela4[[#This Row],[PROJETO]]="CLARO",LEFT(Tabela4[[#This Row],[SITE2]],2),IF(Tabela4[[#This Row],[PROJETO]]="VIVO",RIGHT(LEFT(Tabela4[[#This Row],[SITE2]],10),2),""))
A73: ='BASE FINANCEIRO'!BI111 -> 0 | B73: =MID(A73,36,14) | C73: VIVO | D73: =IF(VLOOKUP('BASE FINANCEIRO'!BC111,'COD. PROJETOS'!B:D,3,0)="VIVO",MID('BASE FINANCEIRO'!BI111,36,3),IF(VLOOKUP('BASE FINANCEIRO'!BC111,'COD. PROJETOS'!B:D,3,0),MID('BASE FINANCEIRO'!BI111,36,7),IF(VLOOKUP('BASE FINANCEIRO'!BC111,'COD. PROJETOS'!B:D,3,0),MID('BASE FINANCEIRO'!BI111,36,9),"PROJETO?"))) -> #N/A | E73: =VLOOKUP(D73,'BASE MUNICÍPIO'!B54:C24789,2,0) -> #N/A | F73: =VLOOKUP(D73,'BASE MUNICÍPIO'!B54:D24789,3,0) -> #N/A | G73: =IF(Tabela4[[#This Row],[PROJETO]]="CLARO",LEFT(Tabela4[[#This Row],[SITE2]],2),IF(Tabela4[[#This Row],[PROJETO]]="VIVO",RIGHT(LEFT(Tabela4[[#This Row],[SITE2]],10),2),""))
A74: ='BASE FINANCEIRO'!BI112 -> 0 | B74: =MID(A74,36,14) | C74: VIVO | D74: =IF(VLOOKUP('BASE FINANCEIRO'!BC112,'COD. PROJETOS'!B:D,3,0)="VIVO",MID('BASE FINANCEIRO'!BI112,36,3),IF(VLOOKUP('BASE FINANCEIRO'!BC112,'COD. PROJETOS'!B:D,3,0),MID('BASE FINANCEIRO'!BI112,36,7),IF(VLOOKUP('BASE FINANCEIRO'!BC112,'COD. PROJETOS'!B:D,3,0),MID('BASE FINANCEIRO'!BI112,36,9),"PROJETO?"))) -> #N/A | E74: =VLOOKUP(D74,'BASE MUNICÍPIO'!B55:C24790,2,0) -> #N/A | F74: =VLOOKUP(D74,'BASE MUNICÍPIO'!B55:D24790,3,0) -> #N/A | G74: =IF(Tabela4[[#This Row],[PROJETO]]="CLARO",LEFT(Tabela4[[#This Row],[SITE2]],2),IF(Tabela4[[#This Row],[PROJETO]]="VIVO",RIGHT(LEFT(Tabela4[[#This Row],[SITE2]],10),2),""))
A75: ='BASE FINANCEIRO'!BI113 -> 0 | B75: =MID(A75,36,14) | C75: VIVO | D75: =IF(VLOOKUP('BASE FINANCEIRO'!BC113,'COD. PROJETOS'!B:D,3,0)="VIVO",MID('BASE FINANCEIRO'!BI113,36,3),IF(VLOOKUP('BASE FINANCEIRO'!BC113,'COD. PROJETOS'!B:D,3,0),MID('BASE FINANCEIRO'!BI113,36,7),IF(VLOOKUP('BASE FINANCEIRO'!BC113,'COD. PROJETOS'!B:D,3,0),MID('BASE FINANCEIRO'!BI113,36,9),"PROJETO?"))) -> #N/A | E75: =VLOOKUP(D75,'BASE MUNICÍPIO'!B56:C24791,2,0) -> #N/A | F75: =VLOOKUP(D75,'BASE MUNICÍPIO'!B56:D24791,3,0) -> #N/A | G75: =IF(Tabela4[[#This Row],[PROJETO]]="CLARO",LEFT(Tabela4[[#This Row],[SITE2]],2),IF(Tabela4[[#This Row],[PROJETO]]="VIVO",RIGHT(LEFT(Tabela4[[#This Row],[SITE2]],10),2),""))
A76: ='BASE FINANCEIRO'!BI114 -> 0 | B76: =MID(A76,36,14) | C76: VIVO | D76: =IF(VLOOKUP('BASE FINANCEIRO'!BC114,'COD. PROJETOS'!B:D,3,0)="VIVO",MID('BASE FINANCEIRO'!BI114,36,3),IF(VLOOKUP('BASE FINANCEIRO'!BC114,'COD. PROJETOS'!B:D,3,0),MID('BASE FINANCEIRO'!BI114,36,7),IF(VLOOKUP('BASE FINANCEIRO'!BC114,'COD. PROJETOS'!B:D,3,0),MID('BASE FINANCEIRO'!BI114,36,9),"PROJETO?"))) -> #N/A | E76: =VLOOKUP(D76,'BASE MUNICÍPIO'!B57:C24792,2,0) -> #N/A | F76: =VLOOKUP(D76,'BASE MUNICÍPIO'!B57:D24792,3,0) -> #N/A | G76: =IF(Tabela4[[#This Row],[PROJETO]]="CLARO",LEFT(Tabela4[[#This Row],[SITE2]],2),IF(Tabela4[[#This Row],[PROJETO]]="VIVO",RIGHT(LEFT(Tabela4[[#This Row],[SITE2]],10),2),""))
A77: ='BASE FINANCEIRO'!BI115 -> 0 | B77: =MID(A77,36,14) | C77: VIVO | D77: =IF(VLOOKUP('BASE FINANCEIRO'!BC115,'COD. PROJETOS'!B:D,3,0)="VIVO",MID('BASE FINANCEIRO'!BI115,36,3),IF(VLOOKUP('BASE FINANCEIRO'!BC115,'COD. PROJETOS'!B:D,3,0),MID('BASE FINANCEIRO'!BI115,36,7),IF(VLOOKUP('BASE FINANCEIRO'!BC115,'COD. PROJETOS'!B:D,3,0),MID('BASE FINANCEIRO'!BI115,36,9),"PROJETO?"))) -> #N/A | E77: =VLOOKUP(D77,'BASE MUNICÍPIO'!B58:C24793,2,0) -> #N/A | F77: =VLOOKUP(D77,'BASE MUNICÍPIO'!B58:D24793,3,0) -> #N/A | G77: =IF(Tabela4[[#This Row],[PROJETO]]="CLARO",LEFT(Tabela4[[#This Row],[SITE2]],2),IF(Tabela4[[#This Row],[PROJETO]]="VIVO",RIGHT(LEFT(Tabela4[[#This Row],[SITE2]],10),2),""))
... A91: ='BASE FINANCEIRO'!BI129 -> 0 | B91: =MID(A91,36,14) | C91: VIVO | D91: =IF(VLOOKUP('BASE FINANCEIRO'!BC129,'COD. PROJETOS'!B:D,3,0)="VIVO",MID('BASE FINANCEIRO'!BI129,36,3),IF(VLOOKUP('BASE FINANCEIRO'!BC129,'COD. PROJETOS'!B:D,3,0),MID('BASE FINANCEIRO'!BI129,36,7),IF(VLOOKUP('BASE FINANCEIRO'!BC129,'COD. PROJETOS'!B:D,3,0),MID('BASE FINANCEIRO'!BI129,36,9),"PROJETO?"))) -> #N/A | E91: =VLOOKUP(D91,'BASE MUNICÍPIO'!B72:C24807,2,0) -> #N/A | F91: =VLOOKUP(D91,'BASE MUNICÍPIO'!B72:D24807,3,0) -> #N/A | G91: =IF(Tabela4[[#This Row],[PROJETO]]="CLARO",LEFT(Tabela4[[#This Row],[SITE2]],2),IF(Tabela4[[#This Row],[PROJETO]]="VIVO",RIGHT(LEFT(Tabela4[[#This Row],[SITE2]],10),2),""))
A92: ='BASE FINANCEIRO'!#REF! -> #REF! | B92: =MID(A92,36,14) -> #REF! | C92: VIVO | D92: =IF(VLOOKUP('BASE FINANCEIRO'!#REF!,'COD. PROJETOS'!B:D,3,0)="VIVO",MID('BASE FINANCEIRO'!#REF!,36,3),IF(VLOOKUP('BASE FINANCEIRO'!#REF!,'COD. PROJETOS'!B:D,3,0),MID('BASE FINANCEIRO'!#REF!,36,7),IF(VLOOKUP('BASE FINANCEIRO'!#REF!,'COD. PROJETOS'!B:D,3,0),MID('BASE FINANCEIRO'!#REF!,36,9),"PROJETO?"))) -> #REF! | E92: =VLOOKUP(D92,'BASE MUNICÍPIO'!B73:C24808,2,0) -> #REF! | F92: =VLOOKUP(D92,'BASE MUNICÍPIO'!B73:D24808,3,0) -> #REF! | G92: =IF(Tabela4[[#This Row],[PROJETO]]="CLARO",LEFT(Tabela4[[#This Row],[SITE2]],2),IF(Tabela4[[#This Row],[PROJETO]]="VIVO",RIGHT(LEFT(Tabela4[[#This Row],[SITE2]],10),2),"")) -> #REF!
A93: ='BASE FINANCEIRO'!BI130 -> 0 | B93: =MID(A93,36,14) | C93: VIVO | D93: =IF(VLOOKUP('BASE FINANCEIRO'!BC130,'COD. PROJETOS'!B:D,3,0)="VIVO",MID('BASE FINANCEIRO'!BI130,36,3),IF(VLOOKUP('BASE FINANCEIRO'!BC130,'COD. PROJETOS'!B:D,3,0),MID('BASE FINANCEIRO'!BI130,36,7),IF(VLOOKUP('BASE FINANCEIRO'!BC130,'COD. PROJETOS'!B:D,3,0),MID('BASE FINANCEIRO'!BI130,36,9),"PROJETO?"))) -> #N/A | E93: =VLOOKUP(D93,'BASE MUNICÍPIO'!B74:C24809,2,0) -> #N/A | F93: =VLOOKUP(D93,'BASE MUNICÍPIO'!B74:D24809,3,0) -> #N/A | G93: =IF(Tabela4[[#This Row],[PROJETO]]="CLARO",LEFT(Tabela4[[#This Row],[SITE2]],2),IF(Tabela4[[#This Row],[PROJETO]]="VIVO",RIGHT(LEFT(Tabela4[[#This Row],[SITE2]],10),2),""))
A94: ='BASE FINANCEIRO'!BI131 -> 0 | B94: =MID(A94,36,14) | C94: VIVO | D94: =IF(VLOOKUP('BASE FINANCEIRO'!BC131,'COD. PROJETOS'!B:D,3,0)="VIVO",MID('BASE FINANCEIRO'!BI131,36,3),IF(VLOOKUP('BASE FINANCEIRO'!BC131,'COD. PROJETOS'!B:D,3,0),MID('BASE FINANCEIRO'!BI131,36,7),IF(VLOOKUP('BASE FINANCEIRO'!BC131,'COD. PROJETOS'!B:D,3,0),MID('BASE FINANCEIRO'!BI131,36,9),"PROJETO?"))) -> #N/A | E94: =VLOOKUP(D94,'BASE MUNICÍPIO'!B75:C24810,2,0) -> #N/A | F94: =VLOOKUP(D94,'BASE MUNICÍPIO'!B75:D24810,3,0) -> #N/A | G94: =IF(Tabela4[[#This Row],[PROJETO]]="CLARO",LEFT(Tabela4[[#This Row],[SITE2]],2),IF(Tabela4[[#This Row],[PROJETO]]="VIVO",RIGHT(LEFT(Tabela4[[#This Row],[SITE2]],10),2),""))
A95: ='BASE FINANCEIRO'!BI132 -> 0 | B95: =MID(A95,36,14) | C95: VIVO | D95: =IF(VLOOKUP('BASE FINANCEIRO'!BC132,'COD. PROJETOS'!B:D,3,0)="VIVO",MID('BASE FINANCEIRO'!BI132,36,3),IF(VLOOKUP('BASE FINANCEIRO'!BC132,'COD. PROJETOS'!B:D,3,0),MID('BASE FINANCEIRO'!BI132,36,7),IF(VLOOKUP('BASE FINANCEIRO'!BC132,'COD. PROJETOS'!B:D,3,0),MID('BASE FINANCEIRO'!BI132,36,9),"PROJETO?"))) -> #N/A | E95: =VLOOKUP(D95,'BASE MUNICÍPIO'!B76:C24811,2,0) -> #N/A | F95: =VLOOKUP(D95,'BASE MUNICÍPIO'!B76:D24811,3,0) -> #N/A | G95: =IF(Tabela4[[#This Row],[PROJETO]]="CLARO",LEFT(Tabela4[[#This Row],[SITE2]],2),IF(Tabela4[[#This Row],[PROJETO]]="VIVO",RIGHT(LEFT(Tabela4[[#This Row],[SITE2]],10),2),""))
A96: ='BASE FINANCEIRO'!BI133 -> 0 | B96: =MID(A96,36,14) | C96: VIVO | D96: =IF(VLOOKUP('BASE FINANCEIRO'!BC133,'COD. PROJETOS'!B:D,3,0)="VIVO",MID('BASE FINANCEIRO'!BI133,36,3),IF(VLOOKUP('BASE FINANCEIRO'!BC133,'COD. PROJETOS'!B:D,3,0),MID('BASE FINANCEIRO'!BI133,36,7),IF(VLOOKUP('BASE FINANCEIRO'!BC133,'COD. PROJETOS'!B:D,3,0),MID('BASE FINANCEIRO'!BI133,36,9),"PROJETO?"))) -> #N/A | E96: =VLOOKUP(D96,'BASE MUNICÍPIO'!B77:C24812,2,0) -> #N/A | F96: =VLOOKUP(D96,'BASE MUNICÍPIO'!B77:D24812,3,0) -> #N/A | G96: =IF(Tabela4[[#This Row],[PROJETO]]="CLARO",LEFT(Tabela4[[#This Row],[SITE2]],2),IF(Tabela4[[#This Row],[PROJETO]]="VIVO",RIGHT(LEFT(Tabela4[[#This Row],[SITE2]],10),2),""))
A97: ='BASE FINANCEIRO'!BI134 -> 0 | B97: =MID(A97,36,14) | C97: VIVO | D97: =IF(VLOOKUP('BASE FINANCEIRO'!BC134,'COD. PROJETOS'!B:D,3,0)="VIVO",MID('BASE FINANCEIRO'!BI134,36,3),IF(VLOOKUP('BASE FINANCEIRO'!BC134,'COD. PROJETOS'!B:D,3,0),MID('BASE FINANCEIRO'!BI134,36,7),IF(VLOOKUP('BASE FINANCEIRO'!BC134,'COD. PROJETOS'!B:D,3,0),MID('BASE FINANCEIRO'!BI134,36,9),"PROJETO?"))) -> #N/A | E97: =VLOOKUP(D97,'BASE MUNICÍPIO'!B78:C24813,2,0) -> #N/A | F97: =VLOOKUP(D97,'BASE MUNICÍPIO'!B78:D24813,3,0) -> #N/A | G97: =IF(Tabela4[[#This Row],[PROJETO]]="CLARO",LEFT(Tabela4[[#This Row],[SITE2]],2),IF(Tabela4[[#This Row],[PROJETO]]="VIVO",RIGHT(LEFT(Tabela4[[#This Row],[SITE2]],10),2),""))
A98: ='BASE FINANCEIRO'!BI135 -> 0 | B98: =MID(A98,36,14) | C98: VIVO | D98: =IF(VLOOKUP('BASE FINANCEIRO'!BC135,'COD. PROJETOS'!B:D,3,0)="VIVO",MID('BASE FINANCEIRO'!BI135,36,3),IF(VLOOKUP('BASE FINANCEIRO'!BC135,'COD. PROJETOS'!B:D,3,0),MID('BASE FINANCEIRO'!BI135,36,7),IF(VLOOKUP('BASE FINANCEIRO'!BC135,'COD. PROJETOS'!B:D,3,0),MID('BASE FINANCEIRO'!BI135,36,9),"PROJETO?"))) -> #N/A | E98: =VLOOKUP(D98,'BASE MUNICÍPIO'!B79:C24814,2,0) -> #N/A | F98: =VLOOKUP(D98,'BASE MUNICÍPIO'!B79:D24814,3,0) -> #N/A | G98: =IF(Tabela4[[#This Row],[PROJETO]]="CLARO",LEFT(Tabela4[[#This Row],[SITE2]],2),IF(Tabela4[[#This Row],[PROJETO]]="VIVO",RIGHT(LEFT(Tabela4[[#This Row],[SITE2]],10),2),""))
A99: ='BASE FINANCEIRO'!BI136 -> 0 | B99: =MID(A99,36,14) | C99: VIVO | D99: =IF(VLOOKUP('BASE FINANCEIRO'!BC136,'COD. PROJETOS'!B:D,3,0)="VIVO",MID('BASE FINANCEIRO'!BI136,36,3),IF(VLOOKUP('BASE FINANCEIRO'!BC136,'COD. PROJETOS'!B:D,3,0),MID('BASE FINANCEIRO'!BI136,36,7),IF(VLOOKUP('BASE FINANCEIRO'!BC136,'COD. PROJETOS'!B:D,3,0),MID('BASE FINANCEIRO'!BI136,36,9),"PROJETO?"))) -> #N/A | E99: =VLOOKUP(D99,'BASE MUNICÍPIO'!B80:C24815,2,0) -> #N/A | F99: =VLOOKUP(D99,'BASE MUNICÍPIO'!B80:D24815,3,0) -> #N/A | G99: =IF(Tabela4[[#This Row],[PROJETO]]="CLARO",LEFT(Tabela4[[#This Row],[SITE2]],2),IF(Tabela4[[#This Row],[PROJETO]]="VIVO",RIGHT(LEFT(Tabela4[[#This Row],[SITE2]],10),2),""))
A100: ='BASE FINANCEIRO'!BI137 -> 0 | B100: =MID(A100,36,14) | C100: VIVO | D100: =IF(VLOOKUP('BASE FINANCEIRO'!BC137,'COD. PROJETOS'!B:D,3,0)="VIVO",MID('BASE FINANCEIRO'!BI137,36,3),IF(VLOOKUP('BASE FINANCEIRO'!BC137,'COD. PROJETOS'!B:D,3,0),MID('BASE FINANCEIRO'!BI137,36,7),IF(VLOOKUP('BASE FINANCEIRO'!BC137,'COD. PROJETOS'!B:D,3,0),MID('BASE FINANCEIRO'!BI137,36,9),"PROJETO?"))) -> #N/A | E100: =VLOOKUP(D100,'BASE MUNICÍPIO'!B81:C24816,2,0) -> #N/A | F100: =VLOOKUP(D100,'BASE MUNICÍPIO'!B81:D24816,3,0) -> #N/A | G100: =IF(Tabela4[[#This Row],[PROJETO]]="CLARO",LEFT(Tabela4[[#This Row],[SITE2]],2),IF(Tabela4[[#This Row],[PROJETO]]="VIVO",RIGHT(LEFT(Tabela4[[#This Row],[SITE2]],10),2),""))
A101: ='BASE FINANCEIRO'!BI138 -> 0 | B101: =MID(A101,36,14) | C101: VIVO | D101: =IF(VLOOKUP('BASE FINANCEIRO'!BC138,'COD. PROJETOS'!B:D,3,0)="VIVO",MID('BASE FINANCEIRO'!BI138,36,3),IF(VLOOKUP('BASE FINANCEIRO'!BC138,'COD. PROJETOS'!B:D,3,0),MID('BASE FINANCEIRO'!BI138,36,7),IF(VLOOKUP('BASE FINANCEIRO'!BC138,'COD. PROJETOS'!B:D,3,0),MID('BASE FINANCEIRO'!BI138,36,9),"PROJETO?"))) -> #N/A | E101: =VLOOKUP(D101,'BASE MUNICÍPIO'!B82:C24817,2,0) -> #N/A | F101: =VLOOKUP(D101,'BASE MUNICÍPIO'!B82:D24817,3,0) -> #N/A | G101: =IF(Tabela4[[#This Row],[PROJETO]]="CLARO",LEFT(Tabela4[[#This Row],[SITE2]],2),IF(Tabela4[[#This Row],[PROJETO]]="VIVO",RIGHT(LEFT(Tabela4[[#This Row],[SITE2]],10),2),""))
A102: ='BASE FINANCEIRO'!BI139 -> 0 | B102: =MID(A102,36,14) | C102: VIVO | D102: =IF(VLOOKUP('BASE FINANCEIRO'!BC139,'COD. PROJETOS'!B:D,3,0)="VIVO",MID('BASE FINANCEIRO'!BI139,36,3),IF(VLOOKUP('BASE FINANCEIRO'!BC139,'COD. PROJETOS'!B:D,3,0),MID('BASE FINANCEIRO'!BI139,36,7),IF(VLOOKUP('BASE FINANCEIRO'!BC139,'COD. PROJETOS'!B:D,3,0),MID('BASE FINANCEIRO'!BI139,36,9),"PROJETO?"))) -> #N/A | E102: =VLOOKUP(D102,'BASE MUNICÍPIO'!B83:C24818,2,0) -> #N/A | F102: =VLOOKUP(D102,'BASE MUNICÍPIO'!B83:D24818,3,0) -> #N/A | G102: =IF(Tabela4[[#This Row],[PROJETO]]="CLARO",LEFT(Tabela4[[#This Row],[SITE2]],2),IF(Tabela4[[#This Row],[PROJETO]]="VIVO",RIGHT(LEFT(Tabela4[[#This Row],[SITE2]],10),2),""))
A103: ='BASE FINANCEIRO'!BI140 -> 0 | B103: =MID(A103,36,14) | C103: VIVO | D103: =IF(VLOOKUP('BASE FINANCEIRO'!BC140,'COD. PROJETOS'!B:D,3,0)="VIVO",MID('BASE FINANCEIRO'!BI140,36,3),IF(VLOOKUP('BASE FINANCEIRO'!BC140,'COD. PROJETOS'!B:D,3,0),MID('BASE FINANCEIRO'!BI140,36,7),IF(VLOOKUP('BASE FINANCEIRO'!BC140,'COD. PROJETOS'!B:D,3,0),MID('BASE FINANCEIRO'!BI140,36,9),"PROJETO?"))) -> #N/A | E103: =VLOOKUP(D103,'BASE MUNICÍPIO'!B84:C24819,2,0) -> #N/A | F103: =VLOOKUP(D103,'BASE MUNICÍPIO'!B84:D24819,3,0) -> #N/A | G103: =IF(Tabela4[[#This Row],[PROJETO]]="CLARO",LEFT(Tabela4[[#This Row],[SITE2]],2),IF(Tabela4[[#This Row],[PROJETO]]="VIVO",RIGHT(LEFT(Tabela4[[#This Row],[SITE2]],10),2),""))
A104: ='BASE FINANCEIRO'!BI141 -> 0 | B104: =MID(A104,36,14) | C104: VIVO | D104: =IF(VLOOKUP('BASE FINANCEIRO'!BC141,'COD. PROJETOS'!B:D,3,0)="VIVO",MID('BASE FINANCEIRO'!BI141,36,3),IF(VLOOKUP('BASE FINANCEIRO'!BC141,'COD. PROJETOS'!B:D,3,0),MID('BASE FINANCEIRO'!BI141,36,7),IF(VLOOKUP('BASE FINANCEIRO'!BC141,'COD. PROJETOS'!B:D,3,0),MID('BASE FINANCEIRO'!BI141,36,9),"PROJETO?"))) -> #N/A | E104: =VLOOKUP(D104,'BASE MUNICÍPIO'!B85:C24820,2,0) -> #N/A | F104: =VLOOKUP(D104,'BASE MUNICÍPIO'!B85:D24820,3,0) -> #N/A | G104: =IF(Tabela4[[#This Row],[PROJETO]]="CLARO",LEFT(Tabela4[[#This Row],[SITE2]],2),IF(Tabela4[[#This Row],[PROJETO]]="VIVO",RIGHT(LEFT(Tabela4[[#This Row],[SITE2]],10),2),""))
... A166: ='BASE FINANCEIRO'!BI203 -> 0 | B166: =MID(A166,36,14) | C166: VIVO | D166: =IF(VLOOKUP('BASE FINANCEIRO'!BC203,'COD. PROJETOS'!B:D,3,0)="VIVO",MID('BASE FINANCEIRO'!BI203,36,3),IF(VLOOKUP('BASE FINANCEIRO'!BC203,'COD. PROJETOS'!B:D,3,0),MID('BASE FINANCEIRO'!BI203,36,7),IF(VLOOKUP('BASE FINANCEIRO'!BC203,'COD. PROJETOS'!B:D,3,0),MID('BASE FINANCEIRO'!BI203,36,9),"PROJETO?"))) -> #N/A | E166: =VLOOKUP(D166,'BASE MUNICÍPIO'!B147:C24882,2,0) -> #N/A | F166: =VLOOKUP(D166,'BASE MUNICÍPIO'!B147:D24882,3,0) -> #N/A | G166: =IF(Tabela4[[#This Row],[PROJETO]]="CLARO",LEFT(Tabela4[[#This Row],[SITE2]],2),IF(Tabela4[[#This Row],[PROJETO]]="VIVO",RIGHT(LEFT(Tabela4[[#This Row],[SITE2]],10),2),""))
A167: ='BASE FINANCEIRO'!#REF! -> #REF! | B167: =MID(A167,36,14) -> #REF! | C167: VIVO | D167: =IF(VLOOKUP('BASE FINANCEIRO'!#REF!,'COD. PROJETOS'!B:D,3,0)="VIVO",MID('BASE FINANCEIRO'!#REF!,36,3),IF(VLOOKUP('BASE FINANCEIRO'!#REF!,'COD. PROJETOS'!B:D,3,0),MID('BASE FINANCEIRO'!#REF!,36,7),IF(VLOOKUP('BASE FINANCEIRO'!#REF!,'COD. PROJETOS'!B:D,3,0),MID('BASE FINANCEIRO'!#REF!,36,9),"PROJETO?"))) -> #REF! | E167: =VLOOKUP(D167,'BASE MUNICÍPIO'!B148:C24883,2,0) -> #REF! | F167: =VLOOKUP(D167,'BASE MUNICÍPIO'!B148:D24883,3,0) -> #REF! | G167: =IF(Tabela4[[#This Row],[PROJETO]]="CLARO",LEFT(Tabela4[[#This Row],[SITE2]],2),IF(Tabela4[[#This Row],[PROJETO]]="VIVO",RIGHT(LEFT(Tabela4[[#This Row],[SITE2]],10),2),"")) -> #REF!
A168: ='BASE FINANCEIRO'!BI204 -> 0 | B168: =MID(A168,36,14) | C168: VIVO | D168: =IF(VLOOKUP('BASE FINANCEIRO'!BC204,'COD. PROJETOS'!B:D,3,0)="VIVO",MID('BASE FINANCEIRO'!BI204,36,3),IF(VLOOKUP('BASE FINANCEIRO'!BC204,'COD. PROJETOS'!B:D,3,0),MID('BASE FINANCEIRO'!BI204,36,7),IF(VLOOKUP('BASE FINANCEIRO'!BC204,'COD. PROJETOS'!B:D,3,0),MID('BASE FINANCEIRO'!BI204,36,9),"PROJETO?"))) -> #N/A | E168: =VLOOKUP(D168,'BASE MUNICÍPIO'!B149:C24884,2,0) -> #N/A | F168: =VLOOKUP(D168,'BASE MUNICÍPIO'!B149:D24884,3,0) -> #N/A | G168: =IF(Tabela4[[#This Row],[PROJETO]]="CLARO",LEFT(Tabela4[[#This Row],[SITE2]],2),IF(Tabela4[[#This Row],[PROJETO]]="VIVO",RIGHT(LEFT(Tabela4[[#This Row],[SITE2]],10),2),""))
A169: ='BASE FINANCEIRO'!BI205 -> 0 | B169: =MID(A169,36,14) | C169: VIVO | D169: =IF(VLOOKUP('BASE FINANCEIRO'!BC205,'COD. PROJETOS'!B:D,3,0)="VIVO",MID('BASE FINANCEIRO'!BI205,36,3),IF(VLOOKUP('BASE FINANCEIRO'!BC205,'COD. PROJETOS'!B:D,3,0),MID('BASE FINANCEIRO'!BI205,36,7),IF(VLOOKUP('BASE FINANCEIRO'!BC205,'COD. PROJETOS'!B:D,3,0),MID('BASE FINANCEIRO'!BI205,36,9),"PROJETO?"))) -> #N/A | E169: =VLOOKUP(D169,'BASE MUNICÍPIO'!B150:C24885,2,0) -> #N/A | F169: =VLOOKUP(D169,'BASE MUNICÍPIO'!B150:D24885,3,0) -> #N/A | G169: =IF(Tabela4[[#This Row],[PROJETO]]="CLARO",LEFT(Tabela4[[#This Row],[SITE2]],2),IF(Tabela4[[#This Row],[PROJETO]]="VIVO",RIGHT(LEFT(Tabela4[[#This Row],[SITE2]],10),2),""))
A170: ='BASE FINANCEIRO'!BI206 -> 0 | B170: =MID(A170,36,14) | C170: VIVO | D170: =IF(VLOOKUP('BASE FINANCEIRO'!BC206,'COD. PROJETOS'!B:D,3,0)="VIVO",MID('BASE FINANCEIRO'!BI206,36,3),IF(VLOOKUP('BASE FINANCEIRO'!BC206,'COD. PROJETOS'!B:D,3,0),MID('BASE FINANCEIRO'!BI206,36,7),IF(VLOOKUP('BASE FINANCEIRO'!BC206,'COD. PROJETOS'!B:D,3,0),MID('BASE FINANCEIRO'!BI206,36,9),"PROJETO?"))) -> #N/A | E170: =VLOOKUP(D170,'BASE MUNICÍPIO'!B151:C24886,2,0) -> #N/A | F170: =VLOOKUP(D170,'BASE MUNICÍPIO'!B151:D24886,3,0) -> #N/A | G170: =IF(Tabela4[[#This Row],[PROJETO]]="CLARO",LEFT(Tabela4[[#This Row],[SITE2]],2),IF(Tabela4[[#This Row],[PROJETO]]="VIVO",RIGHT(LEFT(Tabela4[[#This Row],[SITE2]],10),2),""))
A171: ='BASE FINANCEIRO'!BI207 -> 0 | B171: =MID(A171,36,14) | C171: VIVO | D171: =IF(VLOOKUP('BASE FINANCEIRO'!BC207,'COD. PROJETOS'!B:D,3,0)="VIVO",MID('BASE FINANCEIRO'!BI207,36,3),IF(VLOOKUP('BASE FINANCEIRO'!BC207,'COD. PROJETOS'!B:D,3,0),MID('BASE FINANCEIRO'!BI207,36,7),IF(VLOOKUP('BASE FINANCEIRO'!BC207,'COD. PROJETOS'!B:D,3,0),MID('BASE FINANCEIRO'!BI207,36,9),"PROJETO?"))) -> #N/A | E171: =VLOOKUP(D171,'BASE MUNICÍPIO'!B152:C24887,2,0) -> #N/A | F171: =VLOOKUP(D171,'BASE MUNICÍPIO'!B152:D24887,3,0) -> #N/A | G171: =IF(Tabela4[[#This Row],[PROJETO]]="CLARO",LEFT(Tabela4[[#This Row],[SITE2]],2),IF(Tabela4[[#This Row],[PROJETO]]="VIVO",RIGHT(LEFT(Tabela4[[#This Row],[SITE2]],10),2),""))
A172: ='BASE FINANCEIRO'!BI208 -> 0 | B172: =MID(A172,36,14) | C172: VIVO | D172: =IF(VLOOKUP('BASE FINANCEIRO'!BC208,'COD. PROJETOS'!B:D,3,0)="VIVO",MID('BASE FINANCEIRO'!BI208,36,3),IF(VLOOKUP('BASE FINANCEIRO'!BC208,'COD. PROJETOS'!B:D,3,0),MID('BASE FINANCEIRO'!BI208,36,7),IF(VLOOKUP('BASE FINANCEIRO'!BC208,'COD. PROJETOS'!B:D,3,0),MID('BASE FINANCEIRO'!BI208,36,9),"PROJETO?"))) -> #N/A | E172: =VLOOKUP(D172,'BASE MUNICÍPIO'!B153:C24888,2,0) -> #N/A | F172: =VLOOKUP(D172,'BASE MUNICÍPIO'!B153:D24888,3,0) -> #N/A | G172: =IF(Tabela4[[#This Row],[PROJETO]]="CLARO",LEFT(Tabela4[[#This Row],[SITE2]],2),IF(Tabela4[[#This Row],[PROJETO]]="VIVO",RIGHT(LEFT(Tabela4[[#This Row],[SITE2]],10),2),""))
A173: ='BASE FINANCEIRO'!BI209 -> 0 | B173: =MID(A173,36,14) | C173: VIVO | D173: =IF(VLOOKUP('BASE FINANCEIRO'!BC209,'COD. PROJETOS'!B:D,3,0)="VIVO",MID('BASE FINANCEIRO'!BI209,36,3),IF(VLOOKUP('BASE FINANCEIRO'!BC209,'COD. PROJETOS'!B:D,3,0),MID('BASE FINANCEIRO'!BI209,36,7),IF(VLOOKUP('BASE FINANCEIRO'!BC209,'COD. PROJETOS'!B:D,3,0),MID('BASE FINANCEIRO'!BI209,36,9),"PROJETO?"))) -> #N/A | E173: =VLOOKUP(D173,'BASE MUNICÍPIO'!B154:C24889,2,0) -> #N/A | F173: =VLOOKUP(D173,'BASE MUNICÍPIO'!B154:D24889,3,0) -> #N/A | G173: =IF(Tabela4[[#This Row],[PROJETO]]="CLARO",LEFT(Tabela4[[#This Row],[SITE2]],2),IF(Tabela4[[#This Row],[PROJETO]]="VIVO",RIGHT(LEFT(Tabela4[[#This Row],[SITE2]],10),2),""))
A174: ='BASE FINANCEIRO'!BI210 -> 0 | B174: =MID(A174,36,14) | C174: VIVO | D174: =IF(VLOOKUP('BASE FINANCEIRO'!BC210,'COD. PROJETOS'!B:D,3,0)="VIVO",MID('BASE FINANCEIRO'!BI210,36,3),IF(VLOOKUP('BASE FINANCEIRO'!BC210,'COD. PROJETOS'!B:D,3,0),MID('BASE FINANCEIRO'!BI210,36,7),IF(VLOOKUP('BASE FINANCEIRO'!BC210,'COD. PROJETOS'!B:D,3,0),MID('BASE FINANCEIRO'!BI210,36,9),"PROJETO?"))) -> #N/A | E174: =VLOOKUP(D174,'BASE MUNICÍPIO'!B155:C24890,2,0) -> #N/A | F174: =VLOOKUP(D174,'BASE MUNICÍPIO'!B155:D24890,3,0) -> #N/A | G174: =IF(Tabela4[[#This Row],[PROJETO]]="CLARO",LEFT(Tabela4[[#This Row],[SITE2]],2),IF(Tabela4[[#This Row],[PROJETO]]="VIVO",RIGHT(LEFT(Tabela4[[#This Row],[SITE2]],10),2),""))
A175: ='BASE FINANCEIRO'!#REF! -> #REF! | B175: =MID(A175,36,14) -> #REF! | C175: VIVO | D175: =IF(VLOOKUP('BASE FINANCEIRO'!#REF!,'COD. PROJETOS'!B:D,3,0)="VIVO",MID('BASE FINANCEIRO'!#REF!,36,3),IF(VLOOKUP('BASE FINANCEIRO'!#REF!,'COD. PROJETOS'!B:D,3,0),MID('BASE FINANCEIRO'!#REF!,36,7),IF(VLOOKUP('BASE FINANCEIRO'!#REF!,'COD. PROJETOS'!B:D,3,0),MID('BASE FINANCEIRO'!#REF!,36,9),"PROJETO?"))) -> #REF! | E175: =VLOOKUP(D175,'BASE MUNICÍPIO'!B156:C24891,2,0) -> #REF! | F175: =VLOOKUP(D175,'BASE MUNICÍPIO'!B156:D24891,3,0) -> #REF! | G175: =IF(Tabela4[[#This Row],[PROJETO]]="CLARO",LEFT(Tabela4[[#This Row],[SITE2]],2),IF(Tabela4[[#This Row],[PROJETO]]="VIVO",RIGHT(LEFT(Tabela4[[#This Row],[SITE2]],10),2),"")) -> #REF!
...

Sheet COD.FAT
A1: CW
B2: CODE | C2: TAX CODE
B4: 8818188174 | C4: 7.02
B5: 8818188175 | C5: 7.02
B6: 8818188176 | C6: 7.02
B7: 8818188177 | C7: 7.02
B8: 8818188178 | C8: 7.02
B9: 8818188179 | C9: 7.02
B10: 8818188180 | C10: 7.02
B11: 8818188181 | C11: 7.02
B12: 8818188182 | C12: 7.02
B13: 8818188183 | C13: 7.02
B14: 8818188184 | C14: 7.02
B15: 8818188185 | C15: 7.02
... B126: 8818188291 | C126: 7.02
A127: MW
B128: BOM CODE | C128: TAX CODE
B130: 8812288355 | C130: 7.02
B131: 8812288356 | C131: 7.02
B132: 8812288357 | C132: 7.02
B133: 8812288358 | C133: 7.02
B134: 8812288359 | C134: 7.02
B135: 8812288360 | C135: 7.02
B136: 8812288361 | C136: 7.02
B138: 8812288362 | C138: 7.02
B139: 8812288363 | C139: 7.02
B140: 8812288364 | C140: 7.02
B141: 8812288365 | C141: 7.02
B142: 8812288366 | C142: 7.02
... B191: 8812288401 | C191: 7.02
A192: WL
B193: CODE | C193: TAX CODE
B195: 8812288263 | C195: 7.02
B196: 8812288264 | C196: 7.02
B197: 8812288265 | C197: 7.02
B198: 8812288266 | C198: 7.02
B199: 8812288267 | C199: 7.02
B200: 8812288268 | C200: 7.02
B201: 8812288269 | C201: 7.02
B202: 8812288270 | C202: 7.02
B203: 8812288271 | C203: 7.02
B204: 8812288272 | C204: 7.02
B206: 8812288273 | C206: 7.02
B207: 8812288274 | C207: 7.02
... B922: 8812411575 | C922: 7.03
B923: 88940BXV | C923: 7.03
B924: 88940BXP | C924: 7.02
B925: 8818241104 | C925: 7.02
B926: 8812380455 | C926: 7.02
B927: 8818255112 | C927: 7.02
B928: 8812380288 | C928: 7.02
B929: 8818241142 | C929: 7.02
B930: 8812380281 | C930: 7.02
B931: 8812380292 | C931: 7.02
B932: 8812425494 | C932: 7.02 | E932: 8818241258
B933: 8818241133 | C933: 7.02 | E933: 8812378285
B934: 8812411628 | C934: 7.02 | E934: 8812378287
B935: 8812378287 | C935: 7.02 | E935: 8812425494
B936: 8812378285 | C936: 7.02 | E936: 8812378285
B937: 8812378287 | C937: 7.02 | E937: 8812425494
B938: 8812380378 | C938: 7.02 | E938: 8812378287
B939: 8812411628 | C939: 7.02 | E939: 8818241258
B940: 8812378285 | C940: 7.02 | E940: 8818241258
B941: 8818241137 | C941: 7.02 | E941: 8818241284
B942: 8818241114 | C942: 7.02
B943: 8818241106 | C943: 7.02
B944: 8818241222 | C944: 7.02
B945: 8812399035 | C945: 7.02
B946: 8818113674 | C946: 7.03
B947: 8812380278 | C947: 7.02
B948: 8818241237 | C948: 7.02
B949: 8818241225 | C949: 7.02
B950: 8812380298 | C950: 7.02
B951: 8812099087 | C951: 7.02
B952: 8812411637 | C952: 7.02
B953: 8812380367 | C953: 7.02
... B1113: 8812441752 | C1113: 7.02
B1120: BOM CODE | C1120: Old BOM CODE | D1120: Type | E1120: Payment Terms
B1122: 8812441599 | C1122: 7.03 | D1122: Preliminary | E1122: 100
B1123: 8812441601 | C1123: 7.03 | D1123: Preliminary | E1123: 100
B1124: 8812441603 | C1124: 7.03 | D1124: Preliminary | E1124: 100
B1125: 8812441605 | C1125: 7.03 | D1125: Preliminary | E1125: 100
B1126: 8812441607 | C1126: 7.03 | D1126: Preliminary | E1126: 100
B1127: 8812441609 | C1127: 7.03 | D1127: Preliminary | E1127: 100
B1128: 8812441611 | C1128: 7.03 | D1128: Preliminary | E1128: 100
B1130: 8812441613 | C1130: 7.03 | D1130: SITE VISIT | E1130: 100
B1131: 8812441615 | C1131: 7.03 | D1131: SITE VISIT | E1131: 100
B1132: 8812441617 | C1132: 7.03 | D1132: SITE VISIT | E1132: 100
B1133: 8812441619 | C1133: 7.03 | D1133: SITE VISIT | E1133: 100
B1134: 8812441621 | C1134: 7.03 | D1134: SITE VISIT | E1134: 100
... B1137: 8812441627 | C1137: 7.03 | D1137: SITE VISIT | E1137: 100
B1139: 8812441629 | C1139: 7.02 | D1139: MODEL | E1139: 80/20
B1140: 8812441631 | C1140: 7.02 | D1140: MODEL | E1140: 80/20
B1141: 8812441633 | C1141: 7.02 | D1141: MODEL | E1141: 80/20
B1142: 8812441635 | C1142: 7.02 | D1142: MODEL | E1142: 80/20
B1143: 8812441637 | C1143: 7.02 | D1143: MODEL | E1143: 80/20
B1144: 8812441639 | C1144: 7.02 | D1144: MODEL | E1144: 80/20
B1145: 8812441641 | C1145: 7.02 | D1145: MODEL | E1145: 80/20
B1146: 8812441644 | C1146: 7.02 | D1146: MODEL | E1146: 80/20
B1147: 8812441646 | C1147: 7.02 | D1147: MODEL | E1147: 80/20
...

Sheet BASE CC
B2: UF | C2: TABELA
B3: BA | C3: BA
B4: SE | C4: BA
B5: AL | C5: NE1
B6: PE | C6: NE1
B7: PB | C7: NE1
B8: RN | C8: NE1
B9: CE | C9: NE2
B10: PI | C10: NE2
B11: MA | C11: NE2
B12: DF | C12: CO3
B13: GO | C13: CO3
... B24: MG | C24: MG

Sheet Planilha2
B2: WL
B3: CODE | C3: TAX CODE
B4: 8812288263 | C4: 7.02
B5: 8812288264 | C5: 7.02
B6: 8812288265 | C6: 7.02
B7: 8812288266 | C7: 7.02
B8: 8812288267 | C8: 7.02
B9: 8812288268 | C9: 7.02
B10: 8812288269 | C10: 7.02
B11: 8812288270 | C11: 7.02
B12: 8812288271 | C12: 7.02
B13: 8812288272 | C13: 7.02
B14: 8812288273 | C14: 7.02
B15: 8812288274 | C15: 7.02
B16: 8812288275 | C16: 7.02
B17: 8812288276 | C17: 7.02
B18: 8812288277 | C18: 7.02
B19: 8812288278 | C19: 7.02
... B281: 88940461 | C281: 7.02
